Workbook

Sheet Base de Dados
A1: Código | B1: Cliente | C1: Região | D1: UF | E1: Cidade | F1: Bairro | G1: CEP | H1: Supervisor | I1: Classificação | J1: Distância (km) | K1: Semana | L1: Prioridade | M1: Chave
A2: 1 | B2: PAPELARIA E LIVRARIA FABIJODIV LTDA | C2: CENTRO-OESTE | D2: DF | E2: Brasília | F2: TAGUATINGA | G2: 72130901 | H2: Andressa | I2: Estratégico | J2: 942 | K2: Semana 1 | L2: Alta | M2: chave 1
A3: 2 | B3: NOVA ALIANCA ATACADO LTDA | C3: CENTRO-OESTE | D3: DF | E3: Brasília | F3: TAGUATINGA | G3: 72130075 | H3: Andressa | I3: Estratégico | J3: 942 | K3: Semana 1 | L3: Alta | M3: chave 2
A4: 3 | B4: CENTRO BRASILEIRO DE PESQ. AVAL. E SEL. DE PROMOCAO DE EVENTOS-CEBRASPE | C4: CENTRO-OESTE | D4: DF | E4: BRASÍLIA | F4: ZONA INDUSTRIAL | G4: 70632100 | H4: Andressa | I4: Estratégico | J4: 942 | K4: Semana 1 | L4: Alta | M4: chave 3
A5: 4 | B5: PLANETA DO ESTUDANTE PAPELARIA E LIVRARIA LTDA | C5: CENTRO-OESTE | D5: DF | E5: BRASÍLIA | F5: SAMAMBAIA SUL | G5: 72302537 | H5: Andressa | I5: Estratégico | J5: 942 | K5: Semana 1 | L5: Alta | M5: chave 4
A6: 5 | B6: BENEPAPER COMERCIO DE PAPEIS EIRELI | C6: CENTRO-OESTE | D6: DF | E6: Brasília | F6: PLANALTINA | G6: 73350305 | H6: Andressa | I6: Estratégico | J6: 942 | K6: Semana 1 | L6: Alta | M6: chave 5
A7: 6 | B7: DF PAPELARIA LTDA | C7: CENTRO-OESTE | D7: DF | E7: Brasília | F7: SANTA MARIA | G7: 72546616 | H7: Andressa | I7: Estratégico | J7: 942 | K7: Semana 1 | L7: Alta | M7: chave 6
A8: 7 | B8: BRASIL PROTEC COMERCIO DE PRODUTOS PARA PROTECAO E SAUDE LTDA | C8: CENTRO-OESTE | D8: DF | E8: BRASÍLIA | F8: ASA NORTE | G8: 70714900 | H8: Andressa | I8: Estratégico | J8: 942 | K8: Semana 1 | L8: Alta | M8: chave 7
A9: 8 | B9: J L COMERCIO E DISTRIBUICAO DE UTILIDADES DOMESTICAS LTDA | C9: CENTRO-OESTE | D9: DF | E9: Brasília | F9: TAGUATINGA | G9: 72135180 | H9: Andressa | I9: Estratégico | J9: 942 | K9: Semana 1 | L9: Alta | M9: chave 8
A10: 9 | B10: ALR COMERCIO DE INFORMATICA E PAPELARIA LTDA | C10: CENTRO-OESTE | D10: DF | E10: Brasília | F10: TAGUATINGA NORTE | G10: 72125535 | H10: Andressa | I10: Estratégico | J10: 942 | K10: Semana 1 | L10: Alta | M10: chave 9
A11: 10 | B11: OMNI COMERCIO E SERVICOS LTDA | C11: CENTRO-OESTE | D11: DF | E11: Brasília | F11: ZONA INDUSTRIAL | G11: 70610460 | H11: Andressa | I11: Estratégico | J11: 942 | K11: Semana 1 | L11: Alta | M11: chave 10
A12: 11 | B12: ALMEIDA MENDES COM E CURSOS DE ARTES LTDA | C12: CENTRO-OESTE | D12: DF | E12: Brasília | F12: ASA NORTE | G12: 70722530 | H12: Andressa | I12: Estratégico | J12: 942 | K12: Semana 1 | L12: Alta | M12: chave 11
A13: 12 | B13: ESTILO LIVRARIA E PAPELARIA LTDA | C13: CENTRO-OESTE | D13: DF | E13: Brasília | F13: ST HAB NACIONAL VICENTE PIRES | G13: 72001006 | H13: Andressa | I13: Estratégico | J13: 942 | K13: Semana 1 | L13: Alta | M13: chave 12
... A881: 880 | B881: TEELL-TECNICA E EQUIP. P/ ESCRITORIO LEITE LTDA | C881: SUL | D881: SC | E881: MAFRA | F881: CENTRO | G881: 89300000 | H881: João | I881: Pontual | J881: 1168 | K881: Semana 4 | L881: Normal | M881: chave 880

Sheet Resumo Supervisores
A1: Supervisor | B1: Base Logística | C1: Área de Atuação | D1: Total Clientes | E1: Estratégicos | F1: Fortes | G1: Médios | H1: Pontuais | I1: Distância Média (km)
A2: Andre Pacheco | B2: Fábrica Compactor | C2: RJ Capital e Baixada | D2: =COUNTIF('Base de Dados'!H:H,A2) | E2: =COUNTIFS('Base de Dados'!H:H,A2,'Base de Dados'!I:I,"Estratégico") | F2: =COUNTIFS('Base de Dados'!H:H,A2,'Base de Dados'!I:I,"Forte") | G2: =COUNTIFS('Base de Dados'!H:H,A2,'Base de Dados'!I:I,"Médio") | H2: =COUNTIFS('Base de Dados'!H:H,A2,'Base de Dados'!I:I,"Pontual") | I2: =ROUND(AVERAGEIF('Base de Dados'!H:H,A2,'Base de Dados'!J:J),0)
A3: Andressa | B3: Fábrica Compactor | C3: RJ Serrana/Lagos + MG + GO + DF | D3: =COUNTIF('Base de Dados'!H:H,A3) | E3: =COUNTIFS('Base de Dados'!H:H,A3,'Base de Dados'!I:I,"Estratégico") | F3: =COUNTIFS('Base de Dados'!H:H,A3,'Base de Dados'!I:I,"Forte") | G3: =COUNTIFS('Base de Dados'!H:H,A3,'Base de Dados'!I:I,"Médio") | H3: =COUNTIFS('Base de Dados'!H:H,A3,'Base de Dados'!I:I,"Pontual") | I3: =ROUND(AVERAGEIF('Base de Dados'!H:H,A3,'Base de Dados'!J:J),0)
A4: Bernard | B4: Fábrica Compactor | C4: Espírito Santo | D4: =COUNTIF('Base de Dados'!H:H,A4) | E4: =COUNTIFS('Base de Dados'!H:H,A4,'Base de Dados'!I:I,"Estratégico") | F4: =COUNTIFS('Base de Dados'!H:H,A4,'Base de Dados'!I:I,"Forte") | G4: =COUNTIFS('Base de Dados'!H:H,A4,'Base de Dados'!I:I,"Médio") | H4: =COUNTIFS('Base de Dados'!H:H,A4,'Base de Dados'!I:I,"Pontual") | I4: =ROUND(AVERAGEIF('Base de Dados'!H:H,A4,'Base de Dados'!J:J),0)
A5: Denilson | B5: Fábrica Compactor | C5: São Paulo (Parte 2) | D5: =COUNTIF('Base de Dados'!H:H,A5) | E5: =COUNTIFS('Base de Dados'!H:H,A5,'Base de Dados'!I:I,"Estratégico") | F5: =COUNTIFS('Base de Dados'!H:H,A5,'Base de Dados'!I:I,"Forte") | G5: =COUNTIFS('Base de Dados'!H:H,A5,'Base de Dados'!I:I,"Médio") | H5: =COUNTIFS('Base de Dados'!H:H,A5,'Base de Dados'!I:I,"Pontual") | I5: =ROUND(AVERAGEIF('Base de Dados'!H:H,A5,'Base de Dados'!J:J),0)
A6: Fernanda | B6: São Paulo | C6: São Paulo (Parte 1) | D6: =COUNTIF('Base de Dados'!H:H,A6) | E6: =COUNTIFS('Base de Dados'!H:H,A6,'Base de Dados'!I:I,"Estratégico") | F6: =COUNTIFS('Base de Dados'!H:H,A6,'Base de Dados'!I:I,"Forte") | G6: =COUNTIFS('Base de Dados'!H:H,A6,'Base de Dados'!I:I,"Médio") | H6: =COUNTIFS('Base de Dados'!H:H,A6,'Base de Dados'!I:I,"Pontual") | I6: =ROUND(AVERAGEIF('Base de Dados'!H:H,A6,'Base de Dados'!J:J),0)
A7: João | B7: Fábrica Compactor | C7: Região Sul | D7: =COUNTIF('Base de Dados'!H:H,A7) | E7: =COUNTIFS('Base de Dados'!H:H,A7,'Base de Dados'!I:I,"Estratégico") | F7: =COUNTIFS('Base de Dados'!H:H,A7,'Base de Dados'!I:I,"Forte") | G7: =COUNTIFS('Base de Dados'!H:H,A7,'Base de Dados'!I:I,"Médio") | H7: =COUNTIFS('Base de Dados'!H:H,A7,'Base de Dados'!I:I,"Pontual") | I7: =ROUND(AVERAGEIF('Base de Dados'!H:H,A7,'Base de Dados'!J:J),0)
A8: Rodrigo | B8: Recife | C8: Norte e Nordeste | D8: =COUNTIF('Base de Dados'!H:H,A8) | E8: =COUNTIFS('Base de Dados'!H:H,A8,'Base de Dados'!I:I,"Estratégico") | F8: =COUNTIFS('Base de Dados'!H:H,A8,'Base de Dados'!I:I,"Forte") | G8: =COUNTIFS('Base de Dados'!H:H,A8,'Base de Dados'!I:I,"Médio") | H8: =COUNTIFS('Base de Dados'!H:H,A8,'Base de Dados'!I:I,"Pontual") | I8: =ROUND(AVERAGEIF('Base de Dados'!H:H,A8,'Base de Dados'!J:J),0)
A9: Yan Aragão | B9: Fábrica Compactor | C9: Mato Grosso e MS | D9: =COUNTIF('Base de Dados'!H:H,A9) | E9: =COUNTIFS('Base de Dados'!H:H,A9,'Base de Dados'!I:I,"Estratégico") | F9: =COUNTIFS('Base de Dados'!H:H,A9,'Base de Dados'!I:I,"Forte") | G9: =COUNTIFS('Base de Dados'!H:H,A9,'Base de Dados'!I:I,"Médio") | H9: =COUNTIFS('Base de Dados'!H:H,A9,'Base de Dados'!I:I,"Pontual") | I9: =ROUND(AVERAGEIF('Base de Dados'!H:H,A9,'Base de Dados'!J:J),0)

Sheet Agenda Semanal
A1: Supervisor | B1: Semana | C1: Clientes | D1: Estratégicos | E1: KM Total Estimado
A2: Andre Pacheco | B2: Semana 1 | C2: =COUNTIFS('Base de Dados'!H:H,A2,'Base de Dados'!K:K,B2) | D2: =COUNTIFS('Base de Dados'!H:H,A2,'Base de Dados'!K:K,B2,'Base de Dados'!I:I,"Estratégico") | E2: =SUMIFS('Base de Dados'!J:J,'Base de Dados'!H:H,A2,'Base de Dados'!K:K,B2)
A3: Andre Pacheco | B3: Semana 2 | C3: =COUNTIFS('Base de Dados'!H:H,A3,'Base de Dados'!K:K,B3) | D3: =COUNTIFS('Base de Dados'!H:H,A3,'Base de Dados'!K:K,B3,'Base de Dados'!I:I,"Estratégico") | E3: =SUMIFS('Base de Dados'!J:J,'Base de Dados'!H:H,A3,'Base de Dados'!K:K,B3)
A4: Andre Pacheco | B4: Semana 3 | C4: =COUNTIFS('Base de Dados'!H:H,A4,'Base de Dados'!K:K,B4) | D4: =COUNTIFS('Base de Dados'!H:H,A4,'Base de Dados'!K:K,B4,'Base de Dados'!I:I,"Estratégico") | E4: =SUMIFS('Base de Dados'!J:J,'Base de Dados'!H:H,A4,'Base de Dados'!K:K,B4)
A5: Andre Pacheco | B5: Semana 4 | C5: =COUNTIFS('Base de Dados'!H:H,A5,'Base de Dados'!K:K,B5) | D5: =COUNTIFS('Base de Dados'!H:H,A5,'Base de Dados'!K:K,B5,'Base de Dados'!I:I,"Estratégico") | E5: =SUMIFS('Base de Dados'!J:J,'Base de Dados'!H:H,A5,'Base de Dados'!K:K,B5)
A6: Andressa | B6: Semana 1 | C6: =COUNTIFS('Base de Dados'!H:H,A6,'Base de Dados'!K:K,B6) | D6: =COUNTIFS('Base de Dados'!H:H,A6,'Base de Dados'!K:K,B6,'Base de Dados'!I:I,"Estratégico") | E6: =SUMIFS('Base de Dados'!J:J,'Base de Dados'!H:H,A6,'Base de Dados'!K:K,B6)
A7: Andressa | B7: Semana 2 | C7: =COUNTIFS('Base de Dados'!H:H,A7,'Base de Dados'!K:K,B7) | D7: =COUNTIFS('Base de Dados'!H:H,A7,'Base de Dados'!K:K,B7,'Base de Dados'!I:I,"Estratégico") | E7: =SUMIFS('Base de Dados'!J:J,'Base de Dados'!H:H,A7,'Base de Dados'!K:K,B7)
A8: Andressa | B8: Semana 3 | C8: =COUNTIFS('Base de Dados'!H:H,A8,'Base de Dados'!K:K,B8) | D8: =COUNTIFS('Base de Dados'!H:H,A8,'Base de Dados'!K:K,B8,'Base de Dados'!I:I,"Estratégico") | E8: =SUMIFS('Base de Dados'!J:J,'Base de Dados'!H:H,A8,'Base de Dados'!K:K,B8)
A9: Andressa | B9: Semana 4 | C9: =COUNTIFS('Base de Dados'!H:H,A9,'Base de Dados'!K:K,B9) | D9: =COUNTIFS('Base de Dados'!H:H,A9,'Base de Dados'!K:K,B9,'Base de Dados'!I:I,"Estratégico") | E9: =SUMIFS('Base de Dados'!J:J,'Base de Dados'!H:H,A9,'Base de Dados'!K:K,B9)
A10: Bernard | B10: Semana 1 | C10: =COUNTIFS('Base de Dados'!H:H,A10,'Base de Dados'!K:K,B10) | D10: =COUNTIFS('Base de Dados'!H:H,A10,'Base de Dados'!K:K,B10,'Base de Dados'!I:I,"Estratégico") | E10: =SUMIFS('Base de Dados'!J:J,'Base de Dados'!H:H,A10,'Base de Dados'!K:K,B10)
A11: Bernard | B11: Semana 2 | C11: =COUNTIFS('Base de Dados'!H:H,A11,'Base de Dados'!K:K,B11) | D11: =COUNTIFS('Base de Dados'!H:H,A11,'Base de Dados'!K:K,B11,'Base de Dados'!I:I,"Estratégico") | E11: =SUMIFS('Base de Dados'!J:J,'Base de Dados'!H:H,A11,'Base de Dados'!K:K,B11)
A12: Bernard | B12: Semana 3 | C12: =COUNTIFS('Base de Dados'!H:H,A12,'Base de Dados'!K:K,B12) | D12: =COUNTIFS('Base de Dados'!H:H,A12,'Base de Dados'!K:K,B12,'Base de Dados'!I:I,"Estratégico") | E12: =SUMIFS('Base de Dados'!J:J,'Base de Dados'!H:H,A12,'Base de Dados'!K:K,B12)
A13: Bernard | B13: Semana 4 | C13: =COUNTIFS('Base de Dados'!H:H,A13,'Base de Dados'!K:K,B13) | D13: =COUNTIFS('Base de Dados'!H:H,A13,'Base de Dados'!K:K,B13,'Base de Dados'!I:I,"Estratégico") | E13: =SUMIFS('Base de Dados'!J:J,'Base de Dados'!H:H,A13,'Base de Dados'!K:K,B13)
... A33: Yan Aragão | B33: Semana 4 | C33: =COUNTIFS('Base de Dados'!H:H,A33,'Base de Dados'!K:K,B33) | D33: =COUNTIFS('Base de Dados'!H:H,A33,'Base de Dados'!K:K,B33,'Base de Dados'!I:I,"Estratégico") | E33: =SUMIFS('Base de Dados'!J:J,'Base de Dados'!H:H,A33,'Base de Dados'!K:K,B33)

Sheet Estatísticas por UF
A1: UF | B1: Total Clientes | C1: Supervisor(es) | D1: Estratégicos | E1: Fortes | F1: Médios | G1: Pontuais
A2: AC | B2: =COUNTIF('Base de Dados'!D:D,A2) | C2: Rodrigo | D2: =COUNTIFS('Base de Dados'!D:D,A2,'Base de Dados'!I:I,"Estratégico") | E2: =COUNTIFS('Base de Dados'!D:D,A2,'Base de Dados'!I:I,"Forte") | F2: =COUNTIFS('Base de Dados'!D:D,A2,'Base de Dados'!I:I,"Médio") | G2: =COUNTIFS('Base de Dados'!D:D,A2,'Base de Dados'!I:I,"Pontual")
A3: AL | B3: =COUNTIF('Base de Dados'!D:D,A3) | C3: Rodrigo | D3: =COUNTIFS('Base de Dados'!D:D,A3,'Base de Dados'!I:I,"Estratégico") | E3: =COUNTIFS('Base de Dados'!D:D,A3,'Base de Dados'!I:I,"Forte") | F3: =COUNTIFS('Base de Dados'!D:D,A3,'Base de Dados'!I:I,"Médio") | G3: =COUNTIFS('Base de Dados'!D:D,A3,'Base de Dados'!I:I,"Pontual")
A4: AM | B4: =COUNTIF('Base de Dados'!D:D,A4) | C4: Rodrigo | D4: =COUNTIFS('Base de Dados'!D:D,A4,'Base de Dados'!I:I,"Estratégico") | E4: =COUNTIFS('Base de Dados'!D:D,A4,'Base de Dados'!I:I,"Forte") | F4: =COUNTIFS('Base de Dados'!D:D,A4,'Base de Dados'!I:I,"Médio") | G4: =COUNTIFS('Base de Dados'!D:D,A4,'Base de Dados'!I:I,"Pontual")
A5: AP | B5: =COUNTIF('Base de Dados'!D:D,A5) | C5: Rodrigo | D5: =COUNTIFS('Base de Dados'!D:D,A5,'Base de Dados'!I:I,"Estratégico") | E5: =COUNTIFS('Base de Dados'!D:D,A5,'Base de Dados'!I:I,"Forte") | F5: =COUNTIFS('Base de Dados'!D:D,A5,'Base de Dados'!I:I,"Médio") | G5: =COUNTIFS('Base de Dados'!D:D,A5,'Base de Dados'!I:I,"Pontual")
A6: BA | B6: =COUNTIF('Base de Dados'!D:D,A6) | C6: Rodrigo | D6: =COUNTIFS('Base de Dados'!D:D,A6,'Base de Dados'!I:I,"Estratégico") | E6: =COUNTIFS('Base de Dados'!D:D,A6,'Base de Dados'!I:I,"Forte") | F6: =COUNTIFS('Base de Dados'!D:D,A6,'Base de Dados'!I:I,"Médio") | G6: =COUNTIFS('Base de Dados'!D:D,A6,'Base de Dados'!I:I,"Pontual")
A7: CE | B7: =COUNTIF('Base de Dados'!D:D,A7) | C7: Rodrigo | D7: =COUNTIFS('Base de Dados'!D:D,A7,'Base de Dados'!I:I,"Estratégico") | E7: =COUNTIFS('Base de Dados'!D:D,A7,'Base de Dados'!I:I,"Forte") | F7: =COUNTIFS('Base de Dados'!D:D,A7,'Base de Dados'!I:I,"Médio") | G7: =COUNTIFS('Base de Dados'!D:D,A7,'Base de Dados'!I:I,"Pontual")
A8: DF | B8: =COUNTIF('Base de Dados'!D:D,A8) | C8: Andressa | D8: =COUNTIFS('Base de Dados'!D:D,A8,'Base de Dados'!I:I,"Estratégico") | E8: =COUNTIFS('Base de Dados'!D:D,A8,'Base de Dados'!I:I,"Forte") | F8: =COUNTIFS('Base de Dados'!D:D,A8,'Base de Dados'!I:I,"Médio") | G8: =COUNTIFS('Base de Dados'!D:D,A8,'Base de Dados'!I:I,"Pontual")
A9: ES | B9: =COUNTIF('Base de Dados'!D:D,A9) | C9: Bernard | D9: =COUNTIFS('Base de Dados'!D:D,A9,'Base de Dados'!I:I,"Estratégico") | E9: =COUNTIFS('Base de Dados'!D:D,A9,'Base de Dados'!I:I,"Forte") | F9: =COUNTIFS('Base de Dados'!D:D,A9,'Base de Dados'!I:I,"Médio") | G9: =COUNTIFS('Base de Dados'!D:D,A9,'Base de Dados'!I:I,"Pontual")
A10: GO | B10: =COUNTIF('Base de Dados'!D:D,A10) | C10: Andressa | D10: =COUNTIFS('Base de Dados'!D:D,A10,'Base de Dados'!I:I,"Estratégico") | E10: =COUNTIFS('Base de Dados'!D:D,A10,'Base de Dados'!I:I,"Forte") | F10: =COUNTIFS('Base de Dados'!D:D,A10,'Base de Dados'!I:I,"Médio") | G10: =COUNTIFS('Base de Dados'!D:D,A10,'Base de Dados'!I:I,"Pontual")
A11: MA | B11: =COUNTIF('Base de Dados'!D:D,A11) | C11: Rodrigo | D11: =COUNTIFS('Base de Dados'!D:D,A11,'Base de Dados'!I:I,"Estratégico") | E11: =COUNTIFS('Base de Dados'!D:D,A11,'Base de Dados'!I:I,"Forte") | F11: =COUNTIFS('Base de Dados'!D:D,A11,'Base de Dados'!I:I,"Médio") | G11: =COUNTIFS('Base de Dados'!D:D,A11,'Base de Dados'!I:I,"Pontual")
A12: MG | B12: =COUNTIF('Base de Dados'!D:D,A12) | C12: Andressa | D12: =COUNTIFS('Base de Dados'!D:D,A12,'Base de Dados'!I:I,"Estratégico") | E12: =COUNTIFS('Base de Dados'!D:D,A12,'Base de Dados'!I:I,"Forte") | F12: =COUNTIFS('Base de Dados'!D:D,A12,'Base de Dados'!I:I,"Médio") | G12: =COUNTIFS('Base de Dados'!D:D,A12,'Base de Dados'!I:I,"Pontual")
A13: MS | B13: =COUNTIF('Base de Dados'!D:D,A13) | C13: Yan Aragão | D13: =COUNTIFS('Base de Dados'!D:D,A13,'Base de Dados'!I:I,"Estratégico") | E13: =COUNTIFS('Base de Dados'!D:D,A13,'Base de Dados'!I:I,"Forte") | F13: =COUNTIFS('Base de Dados'!D:D,A13,'Base de Dados'!I:I,"Médio") | G13: =COUNTIFS('Base de Dados'!D:D,A13,'Base de Dados'!I:I,"Pontual")
... A28: TO | B28: =COUNTIF('Base de Dados'!D:D,A28) | C28: Rodrigo | D28: =COUNTIFS('Base de Dados'!D:D,A28,'Base de Dados'!I:I,"Estratégico") | E28: =COUNTIFS('Base de Dados'!D:D,A28,'Base de Dados'!I:I,"Forte") | F28: =COUNTIFS('Base de Dados'!D:D,A28,'Base de Dados'!I:I,"Médio") | G28: =COUNTIFS('Base de Dados'!D:D,A28,'Base de Dados'!I:I,"Pontual")

Sheet Clusters Classificação
A1: Classificação | B1: Total Clientes | C1: % do Total | D1: Prioridade Sugerida
A2: Estratégico | B2: =COUNTIF('Base de Dados'!I:I,A2) | C2: =ROUND(B2/SUM(B$2:B$5)*100,1)&"%" | D2: ALTA - Visitar prioritariamente
A3: Forte | B3: =COUNTIF('Base de Dados'!I:I,A3) | C3: =ROUND(B3/SUM(B$2:B$5)*100,1)&"%" | D3: MÉDIA - Visitar nas primeiras 2 semanas
A4: Médio | B4: =COUNTIF('Base de Dados'!I:I,A4) | C4: =ROUND(B4/SUM(B$2:B$5)*100,1)&"%" | D4: MÉDIA - Distribuir ao longo do mês
A5: Pontual | B5: =COUNTIF('Base de Dados'!I:I,A5) | C5: =ROUND(B5/SUM(B$2:B$5)*100,1)&"%" | D5: NORMAL - Visitar quando em região próxima
A6: TOTAL | B6: =SUM(B2:B5) | C6: 100%

Sheet Dashboard Executivo
A1: DASHBOARD EXECUTIVO - PLANEJAMENTO NACIONAL DE VISITAS
A3: 📊 INDICADORES GERAIS
A4: Total de Clientes | B4: =COUNTA('Base de Dados'!A2:A881)
A5: Total de Supervisores | B5: 8
A6: Total de Estados | B6: 27
A7: Total de Cidades | B7: 476
A9: 🎯 DISTRIBUIÇÃO POR PRIORIDADE
A10: Alta (Estratégicos) | B10: =COUNTIF('Base de Dados'!L:L,"Alta") | C10: =ROUND(B10/B8*100,1)&"%"
A11: Média (Fortes) | B11: =COUNTIF('Base de Dados'!L:L,"Média") | C11: =ROUND(B11/B8*100,1)&"%"
A12: Normal (Demais) | B12: =COUNTIF('Base de Dados'!L:L,"Normal") | C12: =ROUND(B12/B8*100,1)&"%"
A14: 👥 RANKING DE SUPERVISORES (por qtd de clientes)
A15: Supervisor | B15: Clientes
A16: Rodrigo | B16: =COUNTIF('Base de Dados'!H:H,A16)
A17: Andressa | B17: =COUNTIF('Base de Dados'!H:H,A17)
A18: João | B18: =COUNTIF('Base de Dados'!H:H,A18)
A19: Fernanda | B19: =COUNTIF('Base de Dados'!H:H,A19)
A20: Bernard | B20: =COUNTIF('Base de Dados'!H:H,A20)

Sheet Supervisor x Semana
A1: Supervisor | B1: Semana 1 | C1: Semana 2 | D1: Semana 3 | E1: Semana 4 | F1: TOTAL
A2: Andre Pacheco | B2: =COUNTIFS('Base de Dados'!H:H,A2,'Base de Dados'!K:K,"Semana 1") | C2: =COUNTIFS('Base de Dados'!H:H,A2,'Base de Dados'!K:K,"Semana 2") | D2: =COUNTIFS('Base de Dados'!H:H,A2,'Base de Dados'!K:K,"Semana 3") | E2: =COUNTIFS('Base de Dados'!H:H,A2,'Base de Dados'!K:K,"Semana 4") | F2: =SUM(B2:E2)
A3: Andressa | B3: =COUNTIFS('Base de Dados'!H:H,A3,'Base de Dados'!K:K,"Semana 1") | C3: =COUNTIFS('Base de Dados'!H:H,A3,'Base de Dados'!K:K,"Semana 2") | D3: =COUNTIFS('Base de Dados'!H:H,A3,'Base de Dados'!K:K,"Semana 3") | E3: =COUNTIFS('Base de Dados'!H:H,A3,'Base de Dados'!K:K,"Semana 4") | F3: =SUM(B3:E3)
A4: Bernard | B4: =COUNTIFS('Base de Dados'!H:H,A4,'Base de Dados'!K:K,"Semana 1") | C4: =COUNTIFS('Base de Dados'!H:H,A4,'Base de Dados'!K:K,"Semana 2") | D4: =COUNTIFS('Base de Dados'!H:H,A4,'Base de Dados'!K:K,"Semana 3") | E4: =COUNTIFS('Base de Dados'!H:H,A4,'Base de Dados'!K:K,"Semana 4") | F4: =SUM(B4:E4)
A5: Denilson | B5: =COUNTIFS('Base de Dados'!H:H,A5,'Base de Dados'!K:K,"Semana 1") | C5: =COUNTIFS('Base de Dados'!H:H,A5,'Base de Dados'!K:K,"Semana 2") | D5: =COUNTIFS('Base de Dados'!H:H,A5,'Base de Dados'!K:K,"Semana 3") | E5: =COUNTIFS('Base de Dados'!H:H,A5,'Base de Dados'!K:K,"Semana 4") | F5: =SUM(B5:E5)
A6: Fernanda | B6: =COUNTIFS('Base de Dados'!H:H,A6,'Base de Dados'!K:K,"Semana 1") | C6: =COUNTIFS('Base de Dados'!H:H,A6,'Base de Dados'!K:K,"Semana 2") | D6: =COUNTIFS('Base de Dados'!H:H,A6,'Base de Dados'!K:K,"Semana 3") | E6: =COUNTIFS('Base de Dados'!H:H,A6,'Base de Dados'!K:K,"Semana 4") | F6: =SUM(B6:E6)
A7: João | B7: =COUNTIFS('Base de Dados'!H:H,A7,'Base de Dados'!K:K,"Semana 1") | C7: =COUNTIFS('Base de Dados'!H:H,A7,'Base de Dados'!K:K,"Semana 2") | D7: =COUNTIFS('Base de Dados'!H:H,A7,'Base de Dados'!K:K,"Semana 3") | E7: =COUNTIFS('Base de Dados'!H:H,A7,'Base de Dados'!K:K,"Semana 4") | F7: =SUM(B7:E7)
A8: Rodrigo | B8: =COUNTIFS('Base de Dados'!H:H,A8,'Base de Dados'!K:K,"Semana 1") | C8: =COUNTIFS('Base de Dados'!H:H,A8,'Base de Dados'!K:K,"Semana 2") | D8: =COUNTIFS('Base de Dados'!H:H,A8,'Base de Dados'!K:K,"Semana 3") | E8: =COUNTIFS('Base de Dados'!H:H,A8,'Base de Dados'!K:K,"Semana 4") | F8: =SUM(B8:E8)
A9: Yan Aragão | B9: =COUNTIFS('Base de Dados'!H:H,A9,'Base de Dados'!K:K,"Semana 1") | C9: =COUNTIFS('Base de Dados'!H:H,A9,'Base de Dados'!K:K,"Semana 2") | D9: =COUNTIFS('Base de Dados'!H:H,A9,'Base de Dados'!K:K,"Semana 3") | E9: =COUNTIFS('Base de Dados'!H:H,A9,'Base de Dados'!K:K,"Semana 4") | F9: =SUM(B9:E9)
A10: TOTAL | B10: =SUM(B2:B9) | C10: =SUM(C2:C9) | D10: =SUM(D2:D9) | E10: =SUM(E2:E9) | F10: =SUM(F2:F9)

Sheet Modo Transporte
A1: Supervisor | B1: Base | C1: Distância Média (km) | D1: Distância Máxima (km) | E1: Modo Sugerido | F1: Observações
A2: Andre Pacheco | B2: Fábrica Compactor | C2: =ROUND(AVERAGEIF('Base de Dados'!H:H,A2,'Base de Dados'!J:J),0) | D2: =ROUND(MAX(IF('Base de Dados'!$H$2:$H$881=A2,'Base de Dados'!$J$2:$J$881)),0) | E2: =IF(C2<300,"Carro",IF(C2<800,"Carro + Avião ocasional","Avião + Carro")) | F2: Carro/Van - Região metropolitana
A3: Andressa | B3: Fábrica Compactor | C3: =ROUND(AVERAGEIF('Base de Dados'!H:H,A3,'Base de Dados'!J:J),0) | D3: =ROUND(MAX(IF('Base de Dados'!$H$2:$H$881=A3,'Base de Dados'!$J$2:$J$881)),0) | E3: =IF(C3<300,"Carro",IF(C3<800,"Carro + Avião ocasional","Avião + Carro")) | F3: Carro + Avião - Estados distantes (GO/DF)
A4: Bernard | B4: Fábrica Compactor | C4: =ROUND(AVERAGEIF('Base de Dados'!H:H,A4,'Base de Dados'!J:J),0) | D4: =ROUND(MAX(IF('Base de Dados'!$H$2:$H$881=A4,'Base de Dados'!$J$2:$J$881)),0) | E4: =IF(C4<300,"Carro",IF(C4<800,"Carro + Avião ocasional","Avião + Carro")) | F4: Carro - Proximidade da base
A5: Denilson | B5: Fábrica Compactor | C5: =ROUND(AVERAGEIF('Base de Dados'!H:H,A5,'Base de Dados'!J:J),0) | D5: =ROUND(MAX(IF('Base de Dados'!$H$2:$H$881=A5,'Base de Dados'!$J$2:$J$881)),0) | E5: =IF(C5<300,"Carro",IF(C5<800,"Carro + Avião ocasional","Avião + Carro")) | F5: Carro/Avião - Interior de SP
A6: Fernanda | B6: São Paulo | C6: =ROUND(AVERAGEIF('Base de Dados'!H:H,A6,'Base de Dados'!J:J),0) | D6: =ROUND(MAX(IF('Base de Dados'!$H$2:$H$881=A6,'Base de Dados'!$J$2:$J$881)),0) | E6: =IF(C6<300,"Carro",IF(C6<800,"Carro + Avião ocasional","Avião + Carro")) | F6: Carro - Região metropolitana SP
A7: João | B7: Fábrica Compactor | C7: =ROUND(AVERAGEIF('Base de Dados'!H:H,A7,'Base de Dados'!J:J),0) | D7: =ROUND(MAX(IF('Base de Dados'!$H$2:$H$881=A7,'Base de Dados'!$J$2:$J$881)),0) | E7: =IF(C7<300,"Carro",IF(C7<800,"Carro + Avião ocasional","Avião + Carro")) | F7: Avião + Carro - Região Sul
A8: Rodrigo | B8: Recife | C8: =ROUND(AVERAGEIF('Base de Dados'!H:H,A8,'Base de Dados'!J:J),0) | D8: =ROUND(MAX(IF('Base de Dados'!$H$2:$H$881=A8,'Base de Dados'!$J$2:$J$881)),0) | E8: =IF(C8<300,"Carro",IF(C8<800,"Carro + Avião ocasional","Avião + Carro")) | F8: Avião + Carro - Norte e Nordeste
A9: Yan Aragão | B9: Fábrica Compactor | C9: =ROUND(AVERAGEIF('Base de Dados'!H:H,A9,'Base de Dados'!J:J),0) | D9: =ROUND(MAX(IF('Base de Dados'!$H$2:$H$881=A9,'Base de Dados'!$J$2:$J$881)),0) | E9: =IF(C9<300,"Carro",IF(C9<800,"Carro + Avião ocasional","Avião + Carro")) | F9: Avião + Carro - Centro-Oeste

Sheet Densidade por Estado
A1: UF | B1: Região | C1: Total Clientes | D1: Cidades Atendidas | E1: Densidade (Clientes/Cidade) | F1: Classificação Densidade
A2: AC | B2: NORTE | C2: =COUNTIF('Base de Dados'!D:D,A2) | D2: 2 | E2: =ROUND(C2/D2,1) | F2: =IF(E2>=3,"Alta (>3)",IF(E2>=1.5,"Média (1.5-3)","Baixa (<1.5)"))
A3: AL | B3: NORDESTE | C3: =COUNTIF('Base de Dados'!D:D,A3) | D3: 10 | E3: =ROUND(C3/D3,1) | F3: =IF(E3>=3,"Alta (>3)",IF(E3>=1.5,"Média (1.5-3)","Baixa (<1.5)"))
A4: AM | B4: NORTE | C4: =COUNTIF('Base de Dados'!D:D,A4) | D4: 3 | E4: =ROUND(C4/D4,1) | F4: =IF(E4>=3,"Alta (>3)",IF(E4>=1.5,"Média (1.5-3)","Baixa (<1.5)"))
A5: AP | B5: NORTE | C5: =COUNTIF('Base de Dados'!D:D,A5) | D5: 2 | E5: =ROUND(C5/D5,1) | F5: =IF(E5>=3,"Alta (>3)",IF(E5>=1.5,"Média (1.5-3)","Baixa (<1.5)"))
A6: BA | B6: NORDESTE | C6: =COUNTIF('Base de Dados'!D:D,A6) | D6: 26 | E6: =ROUND(C6/D6,1) | F6: =IF(E6>=3,"Alta (>3)",IF(E6>=1.5,"Média (1.5-3)","Baixa (<1.5)"))
A7: CE | B7: NORDESTE | C7: =COUNTIF('Base de Dados'!D:D,A7) | D7: 10 | E7: =ROUND(C7/D7,1) | F7: =IF(E7>=3,"Alta (>3)",IF(E7>=1.5,"Média (1.5-3)","Baixa (<1.5)"))
A8: DF | B8: CENTRO-OESTE | C8: =COUNTIF('Base de Dados'!D:D,A8) | D8: 2 | E8: =ROUND(C8/D8,1) | F8: =IF(E8>=3,"Alta (>3)",IF(E8>=1.5,"Média (1.5-3)","Baixa (<1.5)"))
A9: ES | B9: SUDESTE | C9: =COUNTIF('Base de Dados'!D:D,A9) | D9: 32 | E9: =ROUND(C9/D9,1) | F9: =IF(E9>=3,"Alta (>3)",IF(E9>=1.5,"Média (1.5-3)","Baixa (<1.5)"))
A10: GO | B10: CENTRO-OESTE | C10: =COUNTIF('Base de Dados'!D:D,A10) | D10: 16 | E10: =ROUND(C10/D10,1) | F10: =IF(E10>=3,"Alta (>3)",IF(E10>=1.5,"Média (1.5-3)","Baixa (<1.5)"))
A11: MA | B11: NORDESTE | C11: =COUNTIF('Base de Dados'!D:D,A11) | D11: 9 | E11: =ROUND(C11/D11,1) | F11: =IF(E11>=3,"Alta (>3)",IF(E11>=1.5,"Média (1.5-3)","Baixa (<1.5)"))
A12: MG | B12: SUDESTE | C12: =COUNTIF('Base de Dados'!D:D,A12) | D12: 58 | E12: =ROUND(C12/D12,1) | F12: =IF(E12>=3,"Alta (>3)",IF(E12>=1.5,"Média (1.5-3)","Baixa (<1.5)"))
A13: MS | B13: CENTRO-OESTE | C13: =COUNTIF('Base de Dados'!D:D,A13) | D13: 3 | E13: =ROUND(C13/D13,1) | F13: =IF(E13>=3,"Alta (>3)",IF(E13>=1.5,"Média (1.5-3)","Baixa (<1.5)"))
... A28: TO | B28: NORTE | C28: =COUNTIF('Base de Dados'!D:D,A28) | D28: 7 | E28: =ROUND(C28/D28,1) | F28: =IF(E28>=3,"Alta (>3)",IF(E28>=1.5,"Média (1.5-3)","Baixa (<1.5)"))
A29: TOTAL BRASIL | B29: Todas | C29: =SUM(C2:C28) | D29: =SUM(D2:D28) | E29: =ROUND(C29/D29,1) | F29: Densidade Nacional

Sheet Blocos de Viagem
A1: Bloco | B1: Supervisor | C1: UF | D1: Semana | E1: Clientes | F1: Estratégicos | G1: KM Estimado | H1: Prioridade

Sheet Blocos de Viagem1
A1: Bloco | B1: Supervisor | C1: UF | D1: Semana | E1: Clientes | F1: Estratégicos | G1: KM Estimado | H1: Prioridade
A2: BL-001

Sheet Blocos de Viagem2
A1: Bloco | B1: Supervisor | C1: UF | D1: Semana | E1: Clientes | F1: Estratégicos | G1: KM Estimado | H1: Prioridade
A2: BL-001 | B2: Andre Pacheco | C2: RJ | D2: Semana 1 | E2: =COUNTIFS('Base de Dados'!H:H,B2,'Base de Dados'!D:D,C2,'Base de Dados'!K:K,D2) | F2: =COUNTIFS('Base de Dados'!H:H,B2,'Base de Dados'!D:D,C2,'Base de Dados'!K:K,D2,'Base de Dados'!I:I,"Estratégico") | G2: =SUMIFS('Base de Dados'!J:J,'Base de Dados'!H:H,B2,'Base de Dados'!D:D,C2,'Base de Dados'!K:K,D2) | H2: =IF(F2>=3,"ALTA",IF(F2>=1,"MÉDIA","NORMAL"))
A3: BL-002 | B3: Andre Pacheco | C3: RJ | D3: Semana 2 | E3: =COUNTIFS('Base de Dados'!H:H,B3,'Base de Dados'!D:D,C3,'Base de Dados'!K:K,D3) | F3: =COUNTIFS('Base de Dados'!H:H,B3,'Base de Dados'!D:D,C3,'Base de Dados'!K:K,D3,'Base de Dados'!I:I,"Estratégico") | G3: =SUMIFS('Base de Dados'!J:J,'Base de Dados'!H:H,B3,'Base de Dados'!D:D,C3,'Base de Dados'!K:K,D3) | H3: =IF(F3>=3,"ALTA",IF(F3>=1,"MÉDIA","NORMAL"))
A4: BL-003 | B4: Andre Pacheco | C4: RJ | D4: Semana 3 | E4: =COUNTIFS('Base de Dados'!H:H,B4,'Base de Dados'!D:D,C4,'Base de Dados'!K:K,D4) | F4: =COUNTIFS('Base de Dados'!H:H,B4,'Base de Dados'!D:D,C4,'Base de Dados'!K:K,D4,'Base de Dados'!I:I,"Estratégico") | G4: =SUMIFS('Base de Dados'!J:J,'Base de Dados'!H:H,B4,'Base de Dados'!D:D,C4,'Base de Dados'!K:K,D4) | H4: =IF(F4>=3,"ALTA",IF(F4>=1,"MÉDIA","NORMAL"))
A5: BL-004 | B5: Andre Pacheco | C5: RJ | D5: Semana 4 | E5: =COUNTIFS('Base de Dados'!H:H,B5,'Base de Dados'!D:D,C5,'Base de Dados'!K:K,D5) | F5: =COUNTIFS('Base de Dados'!H:H,B5,'Base de Dados'!D:D,C5,'Base de Dados'!K:K,D5,'Base de Dados'!I:I,"Estratégico") | G5: =SUMIFS('Base de Dados'!J:J,'Base de Dados'!H:H,B5,'Base de Dados'!D:D,C5,'Base de Dados'!K:K,D5) | H5: =IF(F5>=3,"ALTA",IF(F5>=1,"MÉDIA","NORMAL"))
A6: BL-005 | B6: Andressa | C6: RJ | D6: Semana 1 | E6: =COUNTIFS('Base de Dados'!H:H,B6,'Base de Dados'!D:D,C6,'Base de Dados'!K:K,D6) | F6: =COUNTIFS('Base de Dados'!H:H,B6,'Base de Dados'!D:D,C6,'Base de Dados'!K:K,D6,'Base de Dados'!I:I,"Estratégico") | G6: =SUMIFS('Base de Dados'!J:J,'Base de Dados'!H:H,B6,'Base de Dados'!D:D,C6,'Base de Dados'!K:K,D6) | H6: =IF(F6>=3,"ALTA",IF(F6>=1,"MÉDIA","NORMAL"))
A7: BL-006 | B7: Andressa | C7: RJ | D7: Semana 2 | E7: =COUNTIFS('Base de Dados'!H:H,B7,'Base de Dados'!D:D,C7,'Base de Dados'!K:K,D7) | F7: =COUNTIFS('Base de Dados'!H:H,B7,'Base de Dados'!D:D,C7,'Base de Dados'!K:K,D7,'Base de Dados'!I:I,"Estratégico") | G7: =SUMIFS('Base de Dados'!J:J,'Base de Dados'!H:H,B7,'Base de Dados'!D:D,C7,'Base de Dados'!K:K,D7) | H7: =IF(F7>=3,"ALTA",IF(F7>=1,"MÉDIA","NORMAL"))
A8: BL-007 | B8: Andressa | C8: RJ | D8: Semana 3 | E8: =COUNTIFS('Base de Dados'!H:H,B8,'Base de Dados'!D:D,C8,'Base de Dados'!K:K,D8) | F8: =COUNTIFS('Base de Dados'!H:H,B8,'Base de Dados'!D:D,C8,'Base de Dados'!K:K,D8,'Base de Dados'!I:I,"Estratégico") | G8: =SUMIFS('Base de Dados'!J:J,'Base de Dados'!H:H,B8,'Base de Dados'!D:D,C8,'Base de Dados'!K:K,D8) | H8: =IF(F8>=3,"ALTA",IF(F8>=1,"MÉDIA","NORMAL"))
A9: BL-008 | B9: Andressa | C9: RJ | D9: Semana 4 | E9: =COUNTIFS('Base de Dados'!H:H,B9,'Base de Dados'!D:D,C9,'Base de Dados'!K:K,D9) | F9: =COUNTIFS('Base de Dados'!H:H,B9,'Base de Dados'!D:D,C9,'Base de Dados'!K:K,D9,'Base de Dados'!I:I,"Estratégico") | G9: =SUMIFS('Base de Dados'!J:J,'Base de Dados'!H:H,B9,'Base de Dados'!D:D,C9,'Base de Dados'!K:K,D9) | H9: =IF(F9>=3,"ALTA",IF(F9>=1,"MÉDIA","NORMAL"))
A10: BL-009 | B10: Andressa | C10: MG | D10: Semana 1 | E10: =COUNTIFS('Base de Dados'!H:H,B10,'Base de Dados'!D:D,C10,'Base de Dados'!K:K,D10) | F10: =COUNTIFS('Base de Dados'!H:H,B10,'Base de Dados'!D:D,C10,'Base de Dados'!K:K,D10,'Base de Dados'!I:I,"Estratégico") | G10: =SUMIFS('Base de Dados'!J:J,'Base de Dados'!H:H,B10,'Base de Dados'!D:D,C10,'Base de Dados'!K:K,D10) | H10: =IF(F10>=3,"ALTA",IF(F10>=1,"MÉDIA","NORMAL"))
A11: BL-010 | B11: Andressa | C11: MG | D11: Semana 2 | E11: =COUNTIFS('Base de Dados'!H:H,B11,'Base de Dados'!D:D,C11,'Base de Dados'!K:K,D11) | F11: =COUNTIFS('Base de Dados'!H:H,B11,'Base de Dados'!D:D,C11,'Base de Dados'!K:K,D11,'Base de Dados'!I:I,"Estratégico") | G11: =SUMIFS('Base de Dados'!J:J,'Base de Dados'!H:H,B11,'Base de Dados'!D:D,C11,'Base de Dados'!K:K,D11) | H11: =IF(F11>=3,"ALTA",IF(F11>=1,"MÉDIA","NORMAL"))
A12: BL-011 | B12: Andressa | C12: MG | D12: Semana 3 | E12: =COUNTIFS('Base de Dados'!H:H,B12,'Base de Dados'!D:D,C12,'Base de Dados'!K:K,D12) | F12: =COUNTIFS('Base de Dados'!H:H,B12,'Base de Dados'!D:D,C12,'Base de Dados'!K:K,D12,'Base de Dados'!I:I,"Estratégico") | G12: =SUMIFS('Base de Dados'!J:J,'Base de Dados'!H:H,B12,'Base de Dados'!D:D,C12,'Base de Dados'!K:K,D12) | H12: =IF(F12>=3,"ALTA",IF(F12>=1,"MÉDIA","NORMAL"))
A13: BL-012 | B13: Andressa | C13: MG | D13: Semana 4 | E13: =COUNTIFS('Base de Dados'!H:H,B13,'Base de Dados'!D:D,C13,'Base de Dados'!K:K,D13) | F13: =COUNTIFS('Base de Dados'!H:H,B13,'Base de Dados'!D:D,C13,'Base de Dados'!K:K,D13,'Base de Dados'!I:I,"Estratégico") | G13: =SUMIFS('Base de Dados'!J:J,'Base de Dados'!H:H,B13,'Base de Dados'!D:D,C13,'Base de Dados'!K:K,D13) | H13: =IF(F13>=3,"ALTA",IF(F13>=1,"MÉDIA","NORMAL"))
... A61: BL-060 | B61: Yan Aragão | C61: MS | D61: Semana 4 | E61: =COUNTIFS('Base de Dados'!H:H,B61,'Base de Dados'!D:D,C61,'Base de Dados'!K:K,D61) | F61: =COUNTIFS('Base de Dados'!H:H,B61,'Base de Dados'!D:D,C61,'Base de Dados'!K:K,D61,'Base de Dados'!I:I,"Estratégico") | G61: =SUMIFS('Base de Dados'!J:J,'Base de Dados'!H:H,B61,'Base de Dados'!D:D,C61,'Base de Dados'!K:K,D61) | H61: =IF(F61>=3,"ALTA",IF(F61>=1,"MÉDIA","NORMAL"))

Sheet Cluster Cidades
A1: UF | B1: Cidade | C1: Total Clientes | D1: Supervisor(es) | E1: Estratégicos | F1: Fortes | G1: Médios | H1: Pontuais | I1: Tipo Cluster
A2: AC | B2: CRUZEIRO DO SUL | C2: =COUNTIFS('Base de Dados'!D:D,A2,'Base de Dados'!E:E,B2) | D2: Rodrigo | E2: =COUNTIFS('Base de Dados'!D:D,A2,'Base de Dados'!E:E,B2,'Base de Dados'!I:I,"Estratégico") | F2: =COUNTIFS('Base de Dados'!D:D,A2,'Base de Dados'!E:E,B2,'Base de Dados'!I:I,"Forte") | G2: =COUNTIFS('Base de Dados'!D:D,A2,'Base de Dados'!E:E,B2,'Base de Dados'!I:I,"Médio") | H2: =COUNTIFS('Base de Dados'!D:D,A2,'Base de Dados'!E:E,B2,'Base de Dados'!I:I,"Pontual") | I2: =IF(C2>=5,"Cluster Grande (5+)",IF(C2>=3,"Cluster Médio (3-4)",IF(C2>=2,"Cluster Pequeno (2)","Cliente Isolado (1)")))
A3: AC | B3: RIO BRANCO | C3: =COUNTIFS('Base de Dados'!D:D,A3,'Base de Dados'!E:E,B3) | D3: Rodrigo | E3: =COUNTIFS('Base de Dados'!D:D,A3,'Base de Dados'!E:E,B3,'Base de Dados'!I:I,"Estratégico") | F3: =COUNTIFS('Base de Dados'!D:D,A3,'Base de Dados'!E:E,B3,'Base de Dados'!I:I,"Forte") | G3: =COUNTIFS('Base de Dados'!D:D,A3,'Base de Dados'!E:E,B3,'Base de Dados'!I:I,"Médio") | H3: =COUNTIFS('Base de Dados'!D:D,A3,'Base de Dados'!E:E,B3,'Base de Dados'!I:I,"Pontual") | I3: =IF(C3>=5,"Cluster Grande (5+)",IF(C3>=3,"Cluster Médio (3-4)",IF(C3>=2,"Cluster Pequeno (2)","Cliente Isolado (1)")))
A4: AL | B4: ARAPIRACA | C4: =COUNTIFS('Base de Dados'!D:D,A4,'Base de Dados'!E:E,B4) | D4: Rodrigo | E4: =COUNTIFS('Base de Dados'!D:D,A4,'Base de Dados'!E:E,B4,'Base de Dados'!I:I,"Estratégico") | F4: =COUNTIFS('Base de Dados'!D:D,A4,'Base de Dados'!E:E,B4,'Base de Dados'!I:I,"Forte") | G4: =COUNTIFS('Base de Dados'!D:D,A4,'Base de Dados'!E:E,B4,'Base de Dados'!I:I,"Médio") | H4: =COUNTIFS('Base de Dados'!D:D,A4,'Base de Dados'!E:E,B4,'Base de Dados'!I:I,"Pontual") | I4: =IF(C4>=5,"Cluster Grande (5+)",IF(C4>=3,"Cluster Médio (3-4)",IF(C4>=2,"Cluster Pequeno (2)","Cliente Isolado (1)")))
A5: AL | B5: DELMIRO GOUVEIA | C5: =COUNTIFS('Base de Dados'!D:D,A5,'Base de Dados'!E:E,B5) | D5: Rodrigo | E5: =COUNTIFS('Base de Dados'!D:D,A5,'Base de Dados'!E:E,B5,'Base de Dados'!I:I,"Estratégico") | F5: =COUNTIFS('Base de Dados'!D:D,A5,'Base de Dados'!E:E,B5,'Base de Dados'!I:I,"Forte") | G5: =COUNTIFS('Base de Dados'!D:D,A5,'Base de Dados'!E:E,B5,'Base de Dados'!I:I,"Médio") | H5: =COUNTIFS('Base de Dados'!D:D,A5,'Base de Dados'!E:E,B5,'Base de Dados'!I:I,"Pontual") | I5: =IF(C5>=5,"Cluster Grande (5+)",IF(C5>=3,"Cluster Médio (3-4)",IF(C5>=2,"Cluster Pequeno (2)","Cliente Isolado (1)")))
A6: AL | B6: Maceió | C6: =COUNTIFS('Base de Dados'!D:D,A6,'Base de Dados'!E:E,B6) | D6: Rodrigo | E6: =COUNTIFS('Base de Dados'!D:D,A6,'Base de Dados'!E:E,B6,'Base de Dados'!I:I,"Estratégico") | F6: =COUNTIFS('Base de Dados'!D:D,A6,'Base de Dados'!E:E,B6,'Base de Dados'!I:I,"Forte") | G6: =COUNTIFS('Base de Dados'!D:D,A6,'Base de Dados'!E:E,B6,'Base de Dados'!I:I,"Médio") | H6: =COUNTIFS('Base de Dados'!D:D,A6,'Base de Dados'!E:E,B6,'Base de Dados'!I:I,"Pontual") | I6: =IF(C6>=5,"Cluster Grande (5+)",IF(C6>=3,"Cluster Médio (3-4)",IF(C6>=2,"Cluster Pequeno (2)","Cliente Isolado (1)")))
A7: AL | B7: Olho d'Água das Flores | C7: =COUNTIFS('Base de Dados'!D:D,A7,'Base de Dados'!E:E,B7) | D7: Rodrigo | E7: =COUNTIFS('Base de Dados'!D:D,A7,'Base de Dados'!E:E,B7,'Base de Dados'!I:I,"Estratégico") | F7: =COUNTIFS('Base de Dados'!D:D,A7,'Base de Dados'!E:E,B7,'Base de Dados'!I:I,"Forte") | G7: =COUNTIFS('Base de Dados'!D:D,A7,'Base de Dados'!E:E,B7,'Base de Dados'!I:I,"Médio") | H7: =COUNTIFS('Base de Dados'!D:D,A7,'Base de Dados'!E:E,B7,'Base de Dados'!I:I,"Pontual") | I7: =IF(C7>=5,"Cluster Grande (5+)",IF(C7>=3,"Cluster Médio (3-4)",IF(C7>=2,"Cluster Pequeno (2)","Cliente Isolado (1)")))
A8: AL | B8: Palmeira dos Índios | C8: =COUNTIFS('Base de Dados'!D:D,A8,'Base de Dados'!E:E,B8) | D8: Rodrigo | E8: =COUNTIFS('Base de Dados'!D:D,A8,'Base de Dados'!E:E,B8,'Base de Dados'!I:I,"Estratégico") | F8: =COUNTIFS('Base de Dados'!D:D,A8,'Base de Dados'!E:E,B8,'Base de Dados'!I:I,"Forte") | G8: =COUNTIFS('Base de Dados'!D:D,A8,'Base de Dados'!E:E,B8,'Base de Dados'!I:I,"Médio") | H8: =COUNTIFS('Base de Dados'!D:D,A8,'Base de Dados'!E:E,B8,'Base de Dados'!I:I,"Pontual") | I8: =IF(C8>=5,"Cluster Grande (5+)",IF(C8>=3,"Cluster Médio (3-4)",IF(C8>=2,"Cluster Pequeno (2)","Cliente Isolado (1)")))
A9: AL | B9: RIO LARGO | C9: =COUNTIFS('Base de Dados'!D:D,A9,'Base de Dados'!E:E,B9) | D9: Rodrigo | E9: =COUNTIFS('Base de Dados'!D:D,A9,'Base de Dados'!E:E,B9,'Base de Dados'!I:I,"Estratégico") | F9: =COUNTIFS('Base de Dados'!D:D,A9,'Base de Dados'!E:E,B9,'Base de Dados'!I:I,"Forte") | G9: =COUNTIFS('Base de Dados'!D:D,A9,'Base de Dados'!E:E,B9,'Base de Dados'!I:I,"Médio") | H9: =COUNTIFS('Base de Dados'!D:D,A9,'Base de Dados'!E:E,B9,'Base de Dados'!I:I,"Pontual") | I9: =IF(C9>=5,"Cluster Grande (5+)",IF(C9>=3,"Cluster Médio (3-4)",IF(C9>=2,"Cluster Pequeno (2)","Cliente Isolado (1)")))
A10: AL | B10: SANTANA DO IPANEMA | C10: =COUNTIFS('Base de Dados'!D:D,A10,'Base de Dados'!E:E,B10) | D10: Rodrigo | E10: =COUNTIFS('Base de Dados'!D:D,A10,'Base de Dados'!E:E,B10,'Base de Dados'!I:I,"Estratégico") | F10: =COUNTIFS('Base de Dados'!D:D,A10,'Base de Dados'!E:E,B10,'Base de Dados'!I:I,"Forte") | G10: =COUNTIFS('Base de Dados'!D:D,A10,'Base de Dados'!E:E,B10,'Base de Dados'!I:I,"Médio") | H10: =COUNTIFS('Base de Dados'!D:D,A10,'Base de Dados'!E:E,B10,'Base de Dados'!I:I,"Pontual") | I10: =IF(C10>=5,"Cluster Grande (5+)",IF(C10>=3,"Cluster Médio (3-4)",IF(C10>=2,"Cluster Pequeno (2)","Cliente Isolado (1)")))
A11: AL | B11: São José da Tapera | C11: =COUNTIFS('Base de Dados'!D:D,A11,'Base de Dados'!E:E,B11) | D11: Rodrigo | E11: =COUNTIFS('Base de Dados'!D:D,A11,'Base de Dados'!E:E,B11,'Base de Dados'!I:I,"Estratégico") | F11: =COUNTIFS('Base de Dados'!D:D,A11,'Base de Dados'!E:E,B11,'Base de Dados'!I:I,"Forte") | G11: =COUNTIFS('Base de Dados'!D:D,A11,'Base de Dados'!E:E,B11,'Base de Dados'!I:I,"Médio") | H11: =COUNTIFS('Base de Dados'!D:D,A11,'Base de Dados'!E:E,B11,'Base de Dados'!I:I,"Pontual") | I11: =IF(C11>=5,"Cluster Grande (5+)",IF(C11>=3,"Cluster Médio (3-4)",IF(C11>=2,"Cluster Pequeno (2)","Cliente Isolado (1)")))
A12: AL | B12: Teotônio Vilela | C12: =COUNTIFS('Base de Dados'!D:D,A12,'Base de Dados'!E:E,B12) | D12: Rodrigo | E12: =COUNTIFS('Base de Dados'!D:D,A12,'Base de Dados'!E:E,B12,'Base de Dados'!I:I,"Estratégico") | F12: =COUNTIFS('Base de Dados'!D:D,A12,'Base de Dados'!E:E,B12,'Base de Dados'!I:I,"Forte") | G12: =COUNTIFS('Base de Dados'!D:D,A12,'Base de Dados'!E:E,B12,'Base de Dados'!I:I,"Médio") | H12: =COUNTIFS('Base de Dados'!D:D,A12,'Base de Dados'!E:E,B12,'Base de Dados'!I:I,"Pontual") | I12: =IF(C12>=5,"Cluster Grande (5+)",IF(C12>=3,"Cluster Médio (3-4)",IF(C12>=2,"Cluster Pequeno (2)","Cliente Isolado (1)")))
A13: AL | B13: Viçosa | C13: =COUNTIFS('Base de Dados'!D:D,A13,'Base de Dados'!E:E,B13) | D13: Rodrigo | E13: =COUNTIFS('Base de Dados'!D:D,A13,'Base de Dados'!E:E,B13,'Base de Dados'!I:I,"Estratégico") | F13: =COUNTIFS('Base de Dados'!D:D,A13,'Base de Dados'!E:E,B13,'Base de Dados'!I:I,"Forte") | G13: =COUNTIFS('Base de Dados'!D:D,A13,'Base de Dados'!E:E,B13,'Base de Dados'!I:I,"Médio") | H13: =COUNTIFS('Base de Dados'!D:D,A13,'Base de Dados'!E:E,B13,'Base de Dados'!I:I,"Pontual") | I13: =IF(C13>=5,"Cluster Grande (5+)",IF(C13>=3,"Cluster Médio (3-4)",IF(C13>=2,"Cluster Pequeno (2)","Cliente Isolado (1)")))
... A202: PA | B202: GARRAFÃO DO NORTE | C202: =COUNTIFS('Base de Dados'!D:D,A202,'Base de Dados'!E:E,B202) | D202: Rodrigo | E202: =COUNTIFS('Base de Dados'!D:D,A202,'Base de Dados'!E:E,B202,'Base de Dados'!I:I,"Estratégico") | F202: =COUNTIFS('Base de Dados'!D:D,A202,'Base de Dados'!E:E,B202,'Base de Dados'!I:I,"Forte") | G202: =COUNTIFS('Base de Dados'!D:D,A202,'Base de Dados'!E:E,B202,'Base de Dados'!I:I,"Médio") | H202: =COUNTIFS('Base de Dados'!D:D,A202,'Base de Dados'!E:E,B202,'Base de Dados'!I:I,"Pontual") | I202: =IF(C202>=5,"Cluster Grande (5+)",IF(C202>=3,"Cluster Médio (3-4)",IF(C202>=2,"Cluster Pequeno (2)","Cliente Isolado (1)")))
