Workbook

Sheet Base de Dados
A1: Cod Cliente - Matriz | B1: Cliente | C1: Nome Abreviado - Matriz | D1: Supervisor | E1: Região | F1: UF | G1: Repres | H1: Endereço | I1: Cidade | J1: Bairro | K1: CEP | L1: Supervisor | M1: Classificação | N1: Distância (km) | O1: Semana | P1: Prioridade | Q1: CNPJ | R1: Chave
A2: 40448 | B2: PAPELARIA E LIVRARIA FABIJODIV LTDA | C2: FABIJODIV-DF | D2: Andressa | E2: CENTRO-OESTE | F2: DF | G2: 120 - EDSON CARVALHO REPRES DE PAP LTDA | H2: Q QNG AE MERCADO 01 SN | I2: Brasília | J2: TAGUATINGA | K2: 72130901 | L2: Andressa | M2: Estratégico | N2: 942 | O2: Semana 1 | P2: Alta | Q2: 37122090000101 | R2: chave 1
A3: 21124 | B3: NOVA ALIANCA ATACADO LTDA | C3: NOVA-DF | D3: Andressa | E3: CENTRO-OESTE | F3: DF | G3: 120 - EDSON CARVALHO REPRES DE PAP LTDA | H3: CNG 07 LOTE 02 LOJA, 01 | I3: Brasília | J3: TAGUATINGA | K3: 72130075 | L3: Andressa | M3: Estratégico | N3: 942 | O3: Semana 1 | P3: Alta | Q3: 04506629000169 | R3: chave 2
A4: 39733 | B4: CENTRO BRASILEIRO DE PESQ. AVAL. E SEL. DE PROMOCAO DE EVENTOS-CEBRASPE | C4: CEBRASPE-DF | D4: Andressa | E4: CENTRO-OESTE | F4: DF | G4: 120 - EDSON CARVALHO REPRES DE PAP LTDA | H4: Q SAAN QUADRA 1 LTS 1.095, 1.105, 1.115 | I4: BRASÍLIA | J4: ZONA INDUSTRIAL | K4: 70632100 | L4: Andressa | M4: Estratégico | N4: 942 | O4: Semana 1 | P4: Alta | Q4: 18284407000153 | R4: chave 3
A5: 39814 | B5: PLANETA DO ESTUDANTE PAPELARIA E LIVRARIA LTDA | C5: MUNDO/DF | D5: Andressa | E5: CENTRO-OESTE | F5: DF | G5: 120 - EDSON CARVALHO REPRES DE PAP LTDA | H5: Q QS 110 CONJUNTO 7 LOTE 1 2 3 4 5 | I5: BRASÍLIA | J5: SAMAMBAIA SUL | K5: 72302537 | L5: Andressa | M5: Estratégico | N5: 942 | O5: Semana 1 | P5: Alta | Q5: 52361496000122 | R5: chave 4
A6: 35019 | B6: BENEPAPER COMERCIO DE PAPEIS EIRELI | C6: BENEPAPER-DF | D6: Andressa | E6: CENTRO-OESTE | F6: DF | G6: 120 - EDSON CARVALHO REPRES DE PAP LTDA | H6: Q 03, CONJUNTO E, LOTE 21 | I6: Brasília | J6: PLANALTINA | K6: 73350305 | L6: Andressa | M6: Estratégico | N6: 942 | O6: Semana 1 | P6: Alta | Q6: 30142841000102 | R6: chave 5
A7: 36180 | B7: DF PAPELARIA LTDA | C7: DF PAPELARIA | D7: Andressa | E7: CENTRO-OESTE | F7: DF | G7: 120 - EDSON CARVALHO REPRES DE PAP LTDA | H7: QR 316, CONJUNTO P, LOTE 15, LOJA 02 | I7: Brasília | J7: SANTA MARIA | K7: 72546616 | L7: Andressa | M7: Estratégico | N7: 942 | O7: Semana 1 | P7: Alta | Q7: 38001709000184 | R7: chave 6
A8: 37447 | B8: BRASIL PROTEC COMERCIO DE PRODUTOS PARA PROTECAO E SAUDE LTDA | C8: PROTEC-DF | D8: Andressa | E8: CENTRO-OESTE | F8: DF | G8: 120 - EDSON CARVALHO REPRES DE PAP LTDA | H8: Q Q SCN QUADRA 4 BLOCO B SN | I8: BRASÍLIA | J8: ASA NORTE | K8: 70714900 | L8: Andressa | M8: Estratégico | N8: 942 | O8: Semana 1 | P8: Alta | Q8: 36968937000100 | R8: chave 7
A9: 16221 | B9: J L COMERCIO E DISTRIBUICAO DE UTILIDADES DOMESTICAS LTDA | C9: J.L.COMERCIO | D9: Andressa | E9: CENTRO-OESTE | F9: DF | G9: 120 - EDSON CARVALHO REPRES DE PAP LTDA | H9: Q QI 18 S/N LT 29 E 31 | I9: Brasília | J9: TAGUATINGA | K9: 72135180 | L9: Andressa | M9: Estratégico | N9: 942 | O9: Semana 1 | P9: Alta | Q9: 07717596000194 | R9: chave 8
A10: 36367 | B10: ALR COMERCIO DE INFORMATICA E PAPELARIA LTDA | C10: ALR-DF | D10: Andressa | E10: CENTRO-OESTE | F10: DF | G10: 120 - EDSON CARVALHO REPRES DE PAP LTDA | H10: Q CNF 03 LOTE 06 SN LOJA 01 | I10: Brasília | J10: TAGUATINGA NORTE | K10: 72125535 | L10: Andressa | M10: Estratégico | N10: 942 | O10: Semana 1 | P10: Alta | Q10: 06176467000173 | R10: chave 9
A11: 31830 | B11: OMNI COMERCIO E SERVICOS LTDA | C11: OMNI - DF | D11: Andressa | E11: CENTRO-OESTE | F11: DF | G11: 120 - EDSON CARVALHO REPRES DE PAP LTDA | H11: ST SIG QUADRA 6, 2040 | I11: Brasília | J11: ZONA INDUSTRIAL | K11: 70610460 | L11: Andressa | M11: Estratégico | N11: 942 | O11: Semana 1 | P11: Alta | Q11: 38029534000113 | R11: chave 10
A12: 24759 | B12: ALMEIDA MENDES COM E CURSOS DE ARTES LTDA | C12: ALMEIDA-DF | D12: Andressa | E12: CENTRO-OESTE | F12: DF | G12: 120 - EDSON CARVALHO REPRES DE PAP LTDA | H12: Q SHCN CL Q 102 BL C 1 N 102 | I12: Brasília | J12: ASA NORTE | K12: 70722530 | L12: Andressa | M12: Estratégico | N12: 942 | O12: Semana 1 | P12: Alta | Q12: 13727521000197 | R12: chave 11
A13: 22236 | B13: ESTILO LIVRARIA E PAPELARIA LTDA | C13: ESTILO LIV. | D13: Andressa | E13: CENTRO-OESTE | F13: DF | G13: 120 - EDSON CARVALHO REPRES DE PAP LTDA | H13: Q EPTG 01 CONJ 2 LOTE 01 PARTE A | I13: Brasília | J13: ST HAB NACIONAL VICENTE PIRES | K13: 72001006 | L13: Andressa | M13: Estratégico | N13: 942 | O13: Semana 1 | P13: Alta | Q13: 17292060000128 | R13: chave 12
... A881: 843 | B881: TEELL-TECNICA E EQUIP. P/ ESCRITORIO LEITE LTDA | C881: TEELL-TECNIC | D881: João | E881: SUL | F881: SC | G881: 126 - LUIZ CARLOS DIAS MENDIETA | H881: RUA TEN ARY RAUEN, 286 - SALA S | I881: MAFRA | J881: CENTRO | K881: 89300000 | L881: João | M881: Pontual | N881: 1168 | O881: Semana 4 | P881: Normal | Q881: 79849865000187 | R881: chave 880

Sheet Resumo Supervisores
A1: Supervisor | B1: Base Logística | C1: Área de Atuação | D1: Total Clientes | E1: Estados (UF) | F1: Estratégicos | G1: Fortes | H1: Médios | I1: Pontuais | J1: Distância Média (km)
A2: Andre Pacheco | B2: Fábrica Compactor | C2: RJ Capital e Baixada | D2: =COUNTIF('Base de Dados'!L:L,A2) -> 32 | E2: RJ | F2: =COUNTIFS('Base de Dados'!L:L,A2,'Base de Dados'!M:M,"Estratégico") -> 27 | G2: =COUNTIFS('Base de Dados'!L:L,A2,'Base de Dados'!M:M,"Forte") -> 0 | H2: =COUNTIFS('Base de Dados'!L:L,A2,'Base de Dados'!M:M,"Médio") -> 5 | I2: =COUNTIFS('Base de Dados'!L:L,A2,'Base de Dados'!M:M,"Pontual") -> 0 | J2: =ROUND(AVERAGEIF('Base de Dados'!L:L,A2,'Base de Dados'!N:N),0) -> 417
A3: Andressa | B3: Fábrica Compactor | C3: RJ Serrana/Lagos + MG + GO + DF | D3: =COUNTIF('Base de Dados'!L:L,A3) -> 204 | E3: DF, GO, MG, RJ | F3: =COUNTIFS('Base de Dados'!L:L,A3,'Base de Dados'!M:M,"Estratégico") -> 48 | G3: =COUNTIFS('Base de Dados'!L:L,A3,'Base de Dados'!M:M,"Forte") -> 33 | H3: =COUNTIFS('Base de Dados'!L:L,A3,'Base de Dados'!M:M,"Médio") -> 108 | I3: =COUNTIFS('Base de Dados'!L:L,A3,'Base de Dados'!M:M,"Pontual") -> 15 | J3: =ROUND(AVERAGEIF('Base de Dados'!L:L,A3,'Base de Dados'!N:N),0) -> 539
A4: Bernard | B4: Fábrica Compactor | C4: Espírito Santo | D4: =COUNTIF('Base de Dados'!L:L,A4) -> 61 | E4: ES | F4: =COUNTIFS('Base de Dados'!L:L,A4,'Base de Dados'!M:M,"Estratégico") -> 7 | G4: =COUNTIFS('Base de Dados'!L:L,A4,'Base de Dados'!M:M,"Forte") -> 0 | H4: =COUNTIFS('Base de Dados'!L:L,A4,'Base de Dados'!M:M,"Médio") -> 0 | I4: =COUNTIFS('Base de Dados'!L:L,A4,'Base de Dados'!M:M,"Pontual") -> 54 | J4: =ROUND(AVERAGEIF('Base de Dados'!L:L,A4,'Base de Dados'!N:N),0) -> 7
A5: Denilson | B5: Fábrica Compactor | C5: São Paulo (Parte 2) | D5: =COUNTIF('Base de Dados'!L:L,A5) -> 41 | E5: SP | F5: =COUNTIFS('Base de Dados'!L:L,A5,'Base de Dados'!M:M,"Estratégico") -> 6 | G5: =COUNTIFS('Base de Dados'!L:L,A5,'Base de Dados'!M:M,"Forte") -> 14 | H5: =COUNTIFS('Base de Dados'!L:L,A5,'Base de Dados'!M:M,"Médio") -> 21 | I5: =COUNTIFS('Base de Dados'!L:L,A5,'Base de Dados'!M:M,"Pontual") -> 0 | J5: =ROUND(AVERAGEIF('Base de Dados'!L:L,A5,'Base de Dados'!N:N),0) -> 748
A6: Fernanda | B6: São Paulo | C6: São Paulo (Parte 1) | D6: =COUNTIF('Base de Dados'!L:L,A6) -> 63 | E6: SP | F6: =COUNTIFS('Base de Dados'!L:L,A6,'Base de Dados'!M:M,"Estratégico") -> 37 | G6: =COUNTIFS('Base de Dados'!L:L,A6,'Base de Dados'!M:M,"Forte") -> 3 | H6: =COUNTIFS('Base de Dados'!L:L,A6,'Base de Dados'!M:M,"Médio") -> 23 | I6: =COUNTIFS('Base de Dados'!L:L,A6,'Base de Dados'!M:M,"Pontual") -> 0 | J6: =ROUND(AVERAGEIF('Base de Dados'!L:L,A6,'Base de Dados'!N:N),0) -> 0
A7: João | B7: Fábrica Compactor | C7: Região Sul | D7: =COUNTIF('Base de Dados'!L:L,A7) -> 100 | E7: PR, RS, SC | F7: =COUNTIFS('Base de Dados'!L:L,A7,'Base de Dados'!M:M,"Estratégico") -> 17 | G7: =COUNTIFS('Base de Dados'!L:L,A7,'Base de Dados'!M:M,"Forte") -> 12 | H7: =COUNTIFS('Base de Dados'!L:L,A7,'Base de Dados'!M:M,"Médio") -> 0 | I7: =COUNTIFS('Base de Dados'!L:L,A7,'Base de Dados'!M:M,"Pontual") -> 71 | J7: =ROUND(AVERAGEIF('Base de Dados'!L:L,A7,'Base de Dados'!N:N),0) -> 1272
A8: Rodrigo | B8: Recife | C8: Norte e Nordeste | D8: =COUNTIF('Base de Dados'!L:L,A8) -> 356 | E8: AC, AL, AM, AP, BA, CE, MA, PA, PB, PE, PI, RN, RO, RR, SE, TO | F8: =COUNTIFS('Base de Dados'!L:L,A8,'Base de Dados'!M:M,"Estratégico") -> 53 | G8: =COUNTIFS('Base de Dados'!L:L,A8,'Base de Dados'!M:M,"Forte") -> 0 | H8: =COUNTIFS('Base de Dados'!L:L,A8,'Base de Dados'!M:M,"Médio") -> 0 | I8: =COUNTIFS('Base de Dados'!L:L,A8,'Base de Dados'!M:M,"Pontual") -> 303 | J8: =ROUND(AVERAGEIF('Base de Dados'!L:L,A8,'Base de Dados'!N:N),0) -> 1057
A9: Yan Aragão | B9: Fábrica Compactor | C9: Mato Grosso e MS | D9: =COUNTIF('Base de Dados'!L:L,A9) -> 23 | E9: MS, MT | F9: =COUNTIFS('Base de Dados'!L:L,A9,'Base de Dados'!M:M,"Estratégico") -> 0 | G9: =COUNTIFS('Base de Dados'!L:L,A9,'Base de Dados'!M:M,"Forte") -> 0 | H9: =COUNTIFS('Base de Dados'!L:L,A9,'Base de Dados'!M:M,"Médio") -> 0 | I9: =COUNTIFS('Base de Dados'!L:L,A9,'Base de Dados'!M:M,"Pontual") -> 23 | J9: =ROUND(AVERAGEIF('Base de Dados'!L:L,A9,'Base de Dados'!N:N),0) -> 1670

Sheet Agenda Semanal
A1: Supervisor | B1: Semana | C1: Estados | D1: Cidades | E1: Clientes | F1: Estratégicos | G1: KM Total Estimado
A2: Andre Pacheco | B2: Semana 1 | C2: RJ | D2: 2 | E2: =COUNTIFS('Base de Dados'!L:L,A2,'Base de Dados'!O:O,B2) -> 8 | F2: =COUNTIFS('Base de Dados'!L:L,A2,'Base de Dados'!O:O,B2,'Base de Dados'!M:M,"Estratégico") -> 8 | G2: =SUMIFS('Base de Dados'!N:N,'Base de Dados'!L:L,A2,'Base de Dados'!O:O,B2) -> 3336
A3: Andre Pacheco | B3: Semana 2 | C3: RJ | D3: 1 | E3: =COUNTIFS('Base de Dados'!L:L,A3,'Base de Dados'!O:O,B3) -> 8 | F3: =COUNTIFS('Base de Dados'!L:L,A3,'Base de Dados'!O:O,B3,'Base de Dados'!M:M,"Estratégico") -> 8 | G3: =SUMIFS('Base de Dados'!N:N,'Base de Dados'!L:L,A3,'Base de Dados'!O:O,B3) -> 3336
A4: Andre Pacheco | B4: Semana 3 | C4: RJ | D4: 2 | E4: =COUNTIFS('Base de Dados'!L:L,A4,'Base de Dados'!O:O,B4) -> 8 | F4: =COUNTIFS('Base de Dados'!L:L,A4,'Base de Dados'!O:O,B4,'Base de Dados'!M:M,"Estratégico") -> 8 | G4: =SUMIFS('Base de Dados'!N:N,'Base de Dados'!L:L,A4,'Base de Dados'!O:O,B4) -> 3336
A5: Andre Pacheco | B5: Semana 4 | C5: RJ | D5: 6 | E5: =COUNTIFS('Base de Dados'!L:L,A5,'Base de Dados'!O:O,B5) -> 8 | F5: =COUNTIFS('Base de Dados'!L:L,A5,'Base de Dados'!O:O,B5,'Base de Dados'!M:M,"Estratégico") -> 3 | G5: =SUMIFS('Base de Dados'!N:N,'Base de Dados'!L:L,A5,'Base de Dados'!O:O,B5) -> 3336
A6: Andressa | B6: Semana 1 | C6: DF, GO, MG | D6: 7 | E6: =COUNTIFS('Base de Dados'!L:L,A6,'Base de Dados'!O:O,B6) -> 51 | F6: =COUNTIFS('Base de Dados'!L:L,A6,'Base de Dados'!O:O,B6,'Base de Dados'!M:M,"Estratégico") -> 48 | G6: =SUMIFS('Base de Dados'!N:N,'Base de Dados'!L:L,A6,'Base de Dados'!O:O,B6) -> 40508
A7: Andressa | B7: Semana 2 | C7: MG, RJ | D7: 26 | E7: =COUNTIFS('Base de Dados'!L:L,A7,'Base de Dados'!O:O,B7) -> 51 | F7: =COUNTIFS('Base de Dados'!L:L,A7,'Base de Dados'!O:O,B7,'Base de Dados'!M:M,"Estratégico") -> 0 | G7: =SUMIFS('Base de Dados'!N:N,'Base de Dados'!L:L,A7,'Base de Dados'!O:O,B7) -> 20046
A8: Andressa | B8: Semana 3 | C8: MG | D8: 33 | E8: =COUNTIFS('Base de Dados'!L:L,A8,'Base de Dados'!O:O,B8) -> 51 | F8: =COUNTIFS('Base de Dados'!L:L,A8,'Base de Dados'!O:O,B8,'Base de Dados'!M:M,"Estratégico") -> 0 | G8: =SUMIFS('Base de Dados'!N:N,'Base de Dados'!L:L,A8,'Base de Dados'!O:O,B8) -> 19380
A9: Andressa | B9: Semana 4 | C9: GO, MG, RJ | D9: 40 | E9: =COUNTIFS('Base de Dados'!L:L,A9,'Base de Dados'!O:O,B9) -> 51 | F9: =COUNTIFS('Base de Dados'!L:L,A9,'Base de Dados'!O:O,B9,'Base de Dados'!M:M,"Estratégico") -> 0 | G9: =SUMIFS('Base de Dados'!N:N,'Base de Dados'!L:L,A9,'Base de Dados'!O:O,B9) -> 30024
A10: Bernard | B10: Semana 1 | C10: ES | D10: 7 | E10: =COUNTIFS('Base de Dados'!L:L,A10,'Base de Dados'!O:O,B10) -> 15 | F10: =COUNTIFS('Base de Dados'!L:L,A10,'Base de Dados'!O:O,B10,'Base de Dados'!M:M,"Estratégico") -> 7 | G10: =SUMIFS('Base de Dados'!N:N,'Base de Dados'!L:L,A10,'Base de Dados'!O:O,B10) -> 105
A11: Bernard | B11: Semana 2 | C11: ES | D11: 9 | E11: =COUNTIFS('Base de Dados'!L:L,A11,'Base de Dados'!O:O,B11) -> 15 | F11: =COUNTIFS('Base de Dados'!L:L,A11,'Base de Dados'!O:O,B11,'Base de Dados'!M:M,"Estratégico") -> 0 | G11: =SUMIFS('Base de Dados'!N:N,'Base de Dados'!L:L,A11,'Base de Dados'!O:O,B11) -> 105
A12: Bernard | B12: Semana 3 | C12: ES | D12: 8 | E12: =COUNTIFS('Base de Dados'!L:L,A12,'Base de Dados'!O:O,B12) -> 15 | F12: =COUNTIFS('Base de Dados'!L:L,A12,'Base de Dados'!O:O,B12,'Base de Dados'!M:M,"Estratégico") -> 0 | G12: =SUMIFS('Base de Dados'!N:N,'Base de Dados'!L:L,A12,'Base de Dados'!O:O,B12) -> 105
A13: Bernard | B13: Semana 4 | C13: ES | D13: 9 | E13: =COUNTIFS('Base de Dados'!L:L,A13,'Base de Dados'!O:O,B13) -> 16 | F13: =COUNTIFS('Base de Dados'!L:L,A13,'Base de Dados'!O:O,B13,'Base de Dados'!M:M,"Estratégico") -> 0 | G13: =SUMIFS('Base de Dados'!N:N,'Base de Dados'!L:L,A13,'Base de Dados'!O:O,B13) -> 112
... A33: Yan Aragão | B33: Semana 4 | C33: MT | D33: 4 | E33: =COUNTIFS('Base de Dados'!L:L,A33,'Base de Dados'!O:O,B33) -> 8 | F33: =COUNTIFS('Base de Dados'!L:L,A33,'Base de Dados'!O:O,B33,'Base de Dados'!M:M,"Estratégico") -> 0 | G33: =SUMIFS('Base de Dados'!N:N,'Base de Dados'!L:L,A33,'Base de Dados'!O:O,B33) -> 13976

Sheet Roteiro Semanal
A1: Supervisor | B1: Semana | C1: Código | D1: Cliente | E1: UF | F1: Cidade | G1: Classificação | H1: Prioridade | I1: Distância (km)
A2: Andre Pacheco | B2: Semana 1 | C2: 631 | D2: TT BRASIL COMERCIO INTERNACIONAL LTDA | E2: RJ | F2: DUQUE DE CAXIAS | G2: Estratégico | H2: Alta | I2: 417
A3: Andre Pacheco | B3: Semana 1 | C3: 660 | D3: HORIZONTE E-COMMERCE LTDA | E3: RJ | F3: DUQUE DE CAXIAS | G3: Estratégico | H3: Alta | I3: 417
A4: Andre Pacheco | B4: Semana 1 | C4: 665 | D4: GLOBAL ATACADAO COMERCIO LTDA | E4: RJ | F4: DUQUE DE CAXIAS | G4: Estratégico | H4: Alta | I4: 417
A5: Andre Pacheco | B5: Semana 1 | C5: 600 | D5: NOBELESS COMERCIO VAREJISTA 2020 LTDA | E5: RJ | F5: RIO DE JANEIRO | G5: Estratégico | H5: Alta | I5: 417
A6: Andre Pacheco | B6: Semana 1 | C6: 602 | D6: PAPELARIA JARDIM LARGO DO MACHADO LTDA | E6: RJ | F6: RIO DE JANEIRO | G6: Estratégico | H6: Alta | I6: 417
A7: Andre Pacheco | B7: Semana 1 | C7: 606 | D7: LUMYLI COMERCIO VAREJISTA DE PAPELARIA E AVIAMENTOS LTDA | E7: RJ | F7: RIO DE JANEIRO | G7: Estratégico | H7: Alta | I7: 417
A8: Andre Pacheco | B8: Semana 1 | C8: 608 | D8: ARMARINHO DELMAR LTDA | E8: RJ | F8: RIO DE JANEIRO | G8: Estratégico | H8: Alta | I8: 417
A9: Andre Pacheco | B9: Semana 1 | C9: 609 | D9: COISA E TAL DE MADUREIRA PAPELARIA E BAZAR LTDA | E9: RJ | F9: RIO DE JANEIRO | G9: Estratégico | H9: Alta | I9: 417
A10: Andre Pacheco | B10: Semana 2 | C10: 617 | D10: PAPELARIA BAZAR 1 DE MARCO LTDA | E10: RJ | F10: RIO DE JANEIRO | G10: Estratégico | H10: Alta | I10: 417
A11: Andre Pacheco | B11: Semana 2 | C11: 618 | D11: TORRE DE BELEM ART.P/ESCR E PAPELARIA LTDA | E11: RJ | F11: RIO DE JANEIRO | G11: Estratégico | H11: Alta | I11: 417
A12: Andre Pacheco | B12: Semana 2 | C12: 621 | D12: ARMAZEM A FAVORITA LTDA | E12: RJ | F12: RIO DE JANEIRO | G12: Estratégico | H12: Alta | I12: 417
A13: Andre Pacheco | B13: Semana 2 | C13: 634 | D13: BAZAR BRINQUELANDIA LTDA | E13: RJ | F13: RIO DE JANEIRO | G13: Estratégico | H13: Alta | I13: 417
... A881: Yan Aragão | B881: Semana 4 | C881: 66 | D881: JP PAPELARIA MATERIAS DE INFORMATICA LTDA | E881: MT | F881: Várzea Grande | G881: Pontual | H881: Normal | I881: 1747

Sheet Estatísticas por UF
A1: UF | B1: Total Clientes | C1: Supervisor(es) | D1: Estratégicos | E1: Fortes | F1: Médios | G1: Pontuais
A2: AC | B2: =COUNTIF('Base de Dados'!F:F,A2) -> 6 | C2: Rodrigo | D2: =COUNTIFS('Base de Dados'!F:F,A2,'Base de Dados'!M:M,"Estratégico") -> 0 | E2: =COUNTIFS('Base de Dados'!F:F,A2,'Base de Dados'!M:M,"Forte") -> 0 | F2: =COUNTIFS('Base de Dados'!F:F,A2,'Base de Dados'!M:M,"Médio") -> 0 | G2: =COUNTIFS('Base de Dados'!F:F,A2,'Base de Dados'!M:M,"Pontual") -> 6
A3: AL | B3: =COUNTIF('Base de Dados'!F:F,A3) -> 19 | C3: Rodrigo | D3: =COUNTIFS('Base de Dados'!F:F,A3,'Base de Dados'!M:M,"Estratégico") -> 0 | E3: =COUNTIFS('Base de Dados'!F:F,A3,'Base de Dados'!M:M,"Forte") -> 0 | F3: =COUNTIFS('Base de Dados'!F:F,A3,'Base de Dados'!M:M,"Médio") -> 0 | G3: =COUNTIFS('Base de Dados'!F:F,A3,'Base de Dados'!M:M,"Pontual") -> 19
A4: AM | B4: =COUNTIF('Base de Dados'!F:F,A4) -> 27 | C4: Rodrigo | D4: =COUNTIFS('Base de Dados'!F:F,A4,'Base de Dados'!M:M,"Estratégico") -> 25 | E4: =COUNTIFS('Base de Dados'!F:F,A4,'Base de Dados'!M:M,"Forte") -> 0 | F4: =COUNTIFS('Base de Dados'!F:F,A4,'Base de Dados'!M:M,"Médio") -> 0 | G4: =COUNTIFS('Base de Dados'!F:F,A4,'Base de Dados'!M:M,"Pontual") -> 2
A5: AP | B5: =COUNTIF('Base de Dados'!F:F,A5) -> 15 | C5: Rodrigo | D5: =COUNTIFS('Base de Dados'!F:F,A5,'Base de Dados'!M:M,"Estratégico") -> 0 | E5: =COUNTIFS('Base de Dados'!F:F,A5,'Base de Dados'!M:M,"Forte") -> 0 | F5: =COUNTIFS('Base de Dados'!F:F,A5,'Base de Dados'!M:M,"Médio") -> 0 | G5: =COUNTIFS('Base de Dados'!F:F,A5,'Base de Dados'!M:M,"Pontual") -> 15
A6: BA | B6: =COUNTIF('Base de Dados'!F:F,A6) -> 36 | C6: Rodrigo | D6: =COUNTIFS('Base de Dados'!F:F,A6,'Base de Dados'!M:M,"Estratégico") -> 4 | E6: =COUNTIFS('Base de Dados'!F:F,A6,'Base de Dados'!M:M,"Forte") -> 0 | F6: =COUNTIFS('Base de Dados'!F:F,A6,'Base de Dados'!M:M,"Médio") -> 0 | G6: =COUNTIFS('Base de Dados'!F:F,A6,'Base de Dados'!M:M,"Pontual") -> 32
A7: CE | B7: =COUNTIF('Base de Dados'!F:F,A7) -> 20 | C7: Rodrigo | D7: =COUNTIFS('Base de Dados'!F:F,A7,'Base de Dados'!M:M,"Estratégico") -> 8 | E7: =COUNTIFS('Base de Dados'!F:F,A7,'Base de Dados'!M:M,"Forte") -> 0 | F7: =COUNTIFS('Base de Dados'!F:F,A7,'Base de Dados'!M:M,"Médio") -> 0 | G7: =COUNTIFS('Base de Dados'!F:F,A7,'Base de Dados'!M:M,"Pontual") -> 12
A8: DF | B8: =COUNTIF('Base de Dados'!F:F,A8) -> 17 | C8: Andressa | D8: =COUNTIFS('Base de Dados'!F:F,A8,'Base de Dados'!M:M,"Estratégico") -> 17 | E8: =COUNTIFS('Base de Dados'!F:F,A8,'Base de Dados'!M:M,"Forte") -> 0 | F8: =COUNTIFS('Base de Dados'!F:F,A8,'Base de Dados'!M:M,"Médio") -> 0 | G8: =COUNTIFS('Base de Dados'!F:F,A8,'Base de Dados'!M:M,"Pontual") -> 0
A9: ES | B9: =COUNTIF('Base de Dados'!F:F,A9) -> 61 | C9: Bernard | D9: =COUNTIFS('Base de Dados'!F:F,A9,'Base de Dados'!M:M,"Estratégico") -> 7 | E9: =COUNTIFS('Base de Dados'!F:F,A9,'Base de Dados'!M:M,"Forte") -> 0 | F9: =COUNTIFS('Base de Dados'!F:F,A9,'Base de Dados'!M:M,"Médio") -> 0 | G9: =COUNTIFS('Base de Dados'!F:F,A9,'Base de Dados'!M:M,"Pontual") -> 54
A10: GO | B10: =COUNTIF('Base de Dados'!F:F,A10) -> 33 | C10: Andressa | D10: =COUNTIFS('Base de Dados'!F:F,A10,'Base de Dados'!M:M,"Estratégico") -> 18 | E10: =COUNTIFS('Base de Dados'!F:F,A10,'Base de Dados'!M:M,"Forte") -> 0 | F10: =COUNTIFS('Base de Dados'!F:F,A10,'Base de Dados'!M:M,"Médio") -> 0 | G10: =COUNTIFS('Base de Dados'!F:F,A10,'Base de Dados'!M:M,"Pontual") -> 15
A11: MA | B11: =COUNTIF('Base de Dados'!F:F,A11) -> 12 | C11: Rodrigo | D11: =COUNTIFS('Base de Dados'!F:F,A11,'Base de Dados'!M:M,"Estratégico") -> 0 | E11: =COUNTIFS('Base de Dados'!F:F,A11,'Base de Dados'!M:M,"Forte") -> 0 | F11: =COUNTIFS('Base de Dados'!F:F,A11,'Base de Dados'!M:M,"Médio") -> 0 | G11: =COUNTIFS('Base de Dados'!F:F,A11,'Base de Dados'!M:M,"Pontual") -> 12
A12: MG | B12: =COUNTIF('Base de Dados'!F:F,A12) -> 109 | C12: Andressa | D12: =COUNTIFS('Base de Dados'!F:F,A12,'Base de Dados'!M:M,"Estratégico") -> 13 | E12: =COUNTIFS('Base de Dados'!F:F,A12,'Base de Dados'!M:M,"Forte") -> 15 | F12: =COUNTIFS('Base de Dados'!F:F,A12,'Base de Dados'!M:M,"Médio") -> 81 | G12: =COUNTIFS('Base de Dados'!F:F,A12,'Base de Dados'!M:M,"Pontual") -> 0
A13: MS | B13: =COUNTIF('Base de Dados'!F:F,A13) -> 7 | C13: Yan Aragão | D13: =COUNTIFS('Base de Dados'!F:F,A13,'Base de Dados'!M:M,"Estratégico") -> 0 | E13: =COUNTIFS('Base de Dados'!F:F,A13,'Base de Dados'!M:M,"Forte") -> 0 | F13: =COUNTIFS('Base de Dados'!F:F,A13,'Base de Dados'!M:M,"Médio") -> 0 | G13: =COUNTIFS('Base de Dados'!F:F,A13,'Base de Dados'!M:M,"Pontual") -> 7
... A28: TO | B28: =COUNTIF('Base de Dados'!F:F,A28) -> 14 | C28: Rodrigo | D28: =COUNTIFS('Base de Dados'!F:F,A28,'Base de Dados'!M:M,"Estratégico") -> 0 | E28: =COUNTIFS('Base de Dados'!F:F,A28,'Base de Dados'!M:M,"Forte") -> 0 | F28: =COUNTIFS('Base de Dados'!F:F,A28,'Base de Dados'!M:M,"Médio") -> 0 | G28: =COUNTIFS('Base de Dados'!F:F,A28,'Base de Dados'!M:M,"Pontual") -> 14

Sheet Clusters Geográficos
A1: Supervisor | B1: UF | C1: Cidade | D1: Classificação | E1: Qtd Clientes | F1: Distância Média (km)
A2: Andre Pacheco | B2: RJ | C2: DUQUE DE CAXIAS | D2: Estratégico | E2: 3 | F2: 417
A3: Andre Pacheco | B3: RJ | C3: RIO DE JANEIRO | D3: Estratégico | E3: 19 | F3: 417
A4: Andre Pacheco | B4: RJ | C4: Rio de Janeiro | D4: Estratégico | E4: 2 | F4: 417
A5: Andre Pacheco | B5: RJ | C5: SÃO GONÇALO | D5: Estratégico | E5: 2 | F5: 417
A6: Andre Pacheco | B6: RJ | C6: São Gonçalo | D6: Estratégico | E6: 1 | F6: 417
A7: Andre Pacheco | B7: RJ | C7: BELFORD ROXO | D7: Médio | E7: 2 | F7: 417
A8: Andre Pacheco | B8: RJ | C8: Magé | D8: Médio | E8: 1 | F8: 417
A9: Andre Pacheco | B9: RJ | C9: QUEIMADOS | D9: Médio | E9: 1 | F9: 417
A10: Andre Pacheco | B10: RJ | C10: São João de Meriti | D10: Médio | E10: 1 | F10: 417
A11: Andressa | B11: DF | C11: BRASÍLIA | D11: Estratégico | E11: 4 | F11: 942
A12: Andressa | B12: DF | C12: Brasília | D12: Estratégico | E12: 13 | F12: 942
A13: Andressa | B13: GO | C13: Aparecida de Goiânia | D13: Estratégico | E13: 5 | F13: 1023
... A478: Yan Aragão | B478: MT | C478: Várzea Grande | D478: Pontual | E478: 2 | F478: 1747

Sheet Clusters Classificação
A1: Classificação | B1: Total Clientes | C1: % do Total | D1: Prioridade Sugerida
A2: Estratégico | B2: =COUNTIF('Base de Dados'!M:M,A2) -> 195 | C2: =ROUND(B2/SUM(B$2:B$5)*100,1)&"%" -> 22,2% | D2: ALTA - Visitar prioritariamente
A3: Forte | B3: =COUNTIF('Base de Dados'!M:M,A3) -> 62 | C3: =ROUND(B3/SUM(B$2:B$5)*100,1)&"%" -> 7% | D3: MÉDIA - Visitar nas primeiras 2 semanas
A4: Médio | B4: =COUNTIF('Base de Dados'!M:M,A4) -> 157 | C4: =ROUND(B4/SUM(B$2:B$5)*100,1)&"%" -> 17,8% | D4: MÉDIA - Distribuir ao longo do mês
A5: Pontual | B5: =COUNTIF('Base de Dados'!M:M,A5) -> 466 | C5: =ROUND(B5/SUM(B$2:B$5)*100,1)&"%" -> 53% | D5: NORMAL - Visitar quando em região próxima
A6: TOTAL | B6: =SUM(B2:B5) -> 880 | C6: 100%

Sheet Dashboard Executivo
A1: DASHBOARD EXECUTIVO - PLANEJAMENTO NACIONAL DE VISITAS
A3: 📊 INDICADORES GERAIS
A4: Total de Clientes | B4: =COUNTA('Base de Dados'!A2:A881) -> 880
A5: Total de Supervisores | B5: 8
A6: Total de Estados | B6: 27
A7: Total de Cidades | B7: 476
A9: 🎯 DISTRIBUIÇÃO POR PRIORIDADE
A10: Alta (Estratégicos) | B10: =COUNTIF('Base de Dados'!P:P,"Alta") -> 195 | C10: =ROUND(B10/B8*100,1)&"%" -> #DIV/0!
A11: Média (Fortes) | B11: =COUNTIF('Base de Dados'!P:P,"Média") -> 62 | C11: =ROUND(B11/B8*100,1)&"%" -> #DIV/0!
A12: Normal (Demais) | B12: =COUNTIF('Base de Dados'!P:P,"Normal") -> 623 | C12: =ROUND(B12/B8*100,1)&"%" -> #DIV/0!
A14: 👥 RANKING DE SUPERVISORES (por qtd de clientes)
A15: Supervisor | B15: Clientes
A16: Rodrigo | B16: =COUNTIF('Base de Dados'!L:L,A16) -> 356
A17: Andressa | B17: =COUNTIF('Base de Dados'!L:L,A17) -> 204
A18: João | B18: =COUNTIF('Base de Dados'!L:L,A18) -> 100
A19: Fernanda | B19: =COUNTIF('Base de Dados'!L:L,A19) -> 63
A20: Bernard | B20: =COUNTIF('Base de Dados'!L:L,A20) -> 61

Sheet Supervisor x Semana
A1: Supervisor | B1: Semana 1 | C1: Semana 2 | D1: Semana 3 | E1: Semana 4 | F1: TOTAL
A2: Andre Pacheco | B2: =COUNTIFS('Base de Dados'!L:L,A2,'Base de Dados'!O:O,"Semana 1") -> 8 | C2: =COUNTIFS('Base de Dados'!L:L,A2,'Base de Dados'!O:O,"Semana 2") -> 8 | D2: =COUNTIFS('Base de Dados'!L:L,A2,'Base de Dados'!O:O,"Semana 3") -> 8 | E2: =COUNTIFS('Base de Dados'!L:L,A2,'Base de Dados'!O:O,"Semana 4") -> 8 | F2: =SUM(B2:E2) -> 32
A3: Andressa | B3: =COUNTIFS('Base de Dados'!L:L,A3,'Base de Dados'!O:O,"Semana 1") -> 51 | C3: =COUNTIFS('Base de Dados'!L:L,A3,'Base de Dados'!O:O,"Semana 2") -> 51 | D3: =COUNTIFS('Base de Dados'!L:L,A3,'Base de Dados'!O:O,"Semana 3") -> 51 | E3: =COUNTIFS('Base de Dados'!L:L,A3,'Base de Dados'!O:O,"Semana 4") -> 51 | F3: =SUM(B3:E3) -> 204
A4: Bernard | B4: =COUNTIFS('Base de Dados'!L:L,A4,'Base de Dados'!O:O,"Semana 1") -> 15 | C4: =COUNTIFS('Base de Dados'!L:L,A4,'Base de Dados'!O:O,"Semana 2") -> 15 | D4: =COUNTIFS('Base de Dados'!L:L,A4,'Base de Dados'!O:O,"Semana 3") -> 15 | E4: =COUNTIFS('Base de Dados'!L:L,A4,'Base de Dados'!O:O,"Semana 4") -> 16 | F4: =SUM(B4:E4) -> 61
A5: Denilson | B5: =COUNTIFS('Base de Dados'!L:L,A5,'Base de Dados'!O:O,"Semana 1") -> 10 | C5: =COUNTIFS('Base de Dados'!L:L,A5,'Base de Dados'!O:O,"Semana 2") -> 10 | D5: =COUNTIFS('Base de Dados'!L:L,A5,'Base de Dados'!O:O,"Semana 3") -> 10 | E5: =COUNTIFS('Base de Dados'!L:L,A5,'Base de Dados'!O:O,"Semana 4") -> 11 | F5: =SUM(B5:E5) -> 41
A6: Fernanda | B6: =COUNTIFS('Base de Dados'!L:L,A6,'Base de Dados'!O:O,"Semana 1") -> 15 | C6: =COUNTIFS('Base de Dados'!L:L,A6,'Base de Dados'!O:O,"Semana 2") -> 15 | D6: =COUNTIFS('Base de Dados'!L:L,A6,'Base de Dados'!O:O,"Semana 3") -> 15 | E6: =COUNTIFS('Base de Dados'!L:L,A6,'Base de Dados'!O:O,"Semana 4") -> 18 | F6: =SUM(B6:E6) -> 63
A7: João | B7: =COUNTIFS('Base de Dados'!L:L,A7,'Base de Dados'!O:O,"Semana 1") -> 25 | C7: =COUNTIFS('Base de Dados'!L:L,A7,'Base de Dados'!O:O,"Semana 2") -> 25 | D7: =COUNTIFS('Base de Dados'!L:L,A7,'Base de Dados'!O:O,"Semana 3") -> 25 | E7: =COUNTIFS('Base de Dados'!L:L,A7,'Base de Dados'!O:O,"Semana 4") -> 25 | F7: =SUM(B7:E7) -> 100
A8: Rodrigo | B8: =COUNTIFS('Base de Dados'!L:L,A8,'Base de Dados'!O:O,"Semana 1") -> 89 | C8: =COUNTIFS('Base de Dados'!L:L,A8,'Base de Dados'!O:O,"Semana 2") -> 89 | D8: =COUNTIFS('Base de Dados'!L:L,A8,'Base de Dados'!O:O,"Semana 3") -> 89 | E8: =COUNTIFS('Base de Dados'!L:L,A8,'Base de Dados'!O:O,"Semana 4") -> 89 | F8: =SUM(B8:E8) -> 356
A9: Yan Aragão | B9: =COUNTIFS('Base de Dados'!L:L,A9,'Base de Dados'!O:O,"Semana 1") -> 5 | C9: =COUNTIFS('Base de Dados'!L:L,A9,'Base de Dados'!O:O,"Semana 2") -> 5 | D9: =COUNTIFS('Base de Dados'!L:L,A9,'Base de Dados'!O:O,"Semana 3") -> 5 | E9: =COUNTIFS('Base de Dados'!L:L,A9,'Base de Dados'!O:O,"Semana 4") -> 8 | F9: =SUM(B9:E9) -> 23
A10: TOTAL | B10: =SUM(B2:B9) -> 218 | C10: =SUM(C2:C9) -> 218 | D10: =SUM(D2:D9) -> 218 | E10: =SUM(E2:E9) -> 226 | F10: =SUM(F2:F9) -> 880
